[
  {
    "provider_name": "Removery (Sugar Land)",
    "location_city": "Sugar Land",
    "location_state": "TX",
    "method_used": "PicoWay",
    "review_text": "She’s the best",
    "star_rating": 5,
    "review_date": "4 days ago",
    "review_date_iso": "2026-04-23T16:51:55Z",
    "review_date_edited_iso": "2026-04-23T16:51:55Z",
    "reviewer_name": "javier erazo",
    "reviewer_local_guide": true,
    "verified_source": "Google",
    "_place_title": "Removery Tattoo Removal & Fading",
    "_place_id": "ChIJ8yqCOdvnQIYRt8QqQdnlgUw",
    "_scrape_mode": "full",
    "_scrape_date": "2026-04-28",
    "source_url": "https://www.google.com/maps/reviews/data=!4m8!14m7!1m6!2m5!1sCi9DQUlRQUNvZENodHljRjlvT21KQ1VteHNNakZ4YW1Kck9HbG9Sa2syWVZGRWNGRRAB!2m1!1s0x0:0x4c81e5d9412ac4b7!3m1!1s2@1:CAIQACodChtycF9oOmJCUmxsMjFxamJrOGloRkk2YVFEcFE%7C%7C?hl=en-US"
  },
  {
    "provider_name": "Removery (Sugar Land)",
    "location_city": "Sugar Land",
    "location_state": "TX",
    "method_used": "PicoWay",
    "review_text": "",
    "star_rating": 5,
    "review_date": "Edited a week ago",
    "review_date_iso": "2026-02-21T16:49:54Z",
    "review_date_edited_iso": "2026-04-18T17:00:16Z",
    "reviewer_name": "Jorge Guillen",
    "reviewer_local_guide": true,
    "verified_source": "Google",
    "_place_title": "Removery Tattoo Removal & Fading",
    "_place_id": "ChIJ8yqCOdvnQIYRt8QqQdnlgUw",
    "_scrape_mode": "full",
    "_scrape_date": "2026-04-28",
    "source_url": "https://www.google.com/maps/reviews/data=!4m8!14m7!1m6!2m5!1sCi9DQUlRQUNvZENodHljRjlvT2xwRlpGTkpkbEpyTnpaRFYwUlNXRGhYYTBKMmVuYxAB!2m1!1s0x0:0x4c81e5d9412ac4b7!3m1!1s2@1:CAIQACodChtycF9oOlpFZFNJdlJrNzZDV0RSWDhXa0J2enc%7C%7C?hl=en-US"
  },
  {
    "provider_name": "Removery (Sugar Land)",
    "location_city": "Sugar Land",
    "location_state": "TX",
    "method_used": "PicoWay",
    "review_text": "My experience was actually quick & overall the pain was not as bad as I thought it would be . Highly recommend def worth the results",
    "star_rating": 5,
    "review_date": "Edited a week ago",
    "review_date_iso": "2025-10-07T21:12:20Z",
    "review_date_edited_iso": "2026-04-16T16:26:59Z",
    "reviewer_name": "Alexandra Bonnie",
    "reviewer_local_guide": true,
    "verified_source": "Google",
    "_place_title": "Removery Tattoo Removal & Fading",
    "_place_id": "ChIJ8yqCOdvnQIYRt8QqQdnlgUw",
    "_scrape_mode": "full",
    "_scrape_date": "2026-04-28",
    "source_url": "https://www.google.com/maps/reviews/data=!4m8!14m7!1m6!2m5!1sCi9DQUlRQUNvZENodHljRjlvT2tGNmJIbDFUMmxyYjB0ZlUyWnNSak5zTmtodVJWRRAB!2m1!1s0x0:0x4c81e5d9412ac4b7!3m1!1s2@1:CAIQACodChtycF9oOkF6bHl1T2lrb0tfU2ZsRjNsNkhuRVE%7C%7C?hl=en-US"
  },
  {
    "provider_name": "Removery (Sugar Land)",
    "location_city": "Sugar Land",
    "location_state": "TX",
    "method_used": "PicoWay",
    "review_text": "Excelent",
    "star_rating": 5,
    "review_date": "a week ago",
    "review_date_iso": "2026-04-14T20:46:28Z",
    "review_date_edited_iso": "2026-04-14T20:46:28Z",
    "reviewer_name": "Ronald Torres Chupin",
    "reviewer_local_guide": true,
    "verified_source": "Google",
    "_place_title": "Removery Tattoo Removal & Fading",
    "_place_id": "ChIJ8yqCOdvnQIYRt8QqQdnlgUw",
    "_scrape_mode": "full",
    "_scrape_date": "2026-04-28",
    "source_url": "https://www.google.com/maps/reviews/data=!4m8!14m7!1m6!2m5!1sCi9DQUlRQUNvZENodHljRjlvT205QlFsOXRkVk5wTm1adVdYbHVPR3BYTFVkUU0zYxAB!2m1!1s0x0:0x4c81e5d9412ac4b7!3m1!1s2@1:CAIQACodChtycF9oOm9BQl9tdVNpNmZuWXluOGpXLUdQM3c%7C%7C?hl=en-US"
  },
  {
    "provider_name": "Removery (Sugar Land)",
    "location_city": "Sugar Land",
    "location_state": "TX",
    "method_used": "PicoWay",
    "review_text": "Great place to get your tattoos removed. Great staff and very professional.",
    "star_rating": 5,
    "review_date": "3 weeks ago",
    "review_date_iso": "2026-04-04T17:31:34Z",
    "review_date_edited_iso": "2026-04-04T17:31:34Z",
    "reviewer_name": "Eric L",
    "reviewer_local_guide": true,
    "verified_source": "Google",
    "_place_title": "Removery Tattoo Removal & Fading",
    "_place_id": "ChIJ8yqCOdvnQIYRt8QqQdnlgUw",
    "_scrape_mode": "full",
    "_scrape_date": "2026-04-28",
    "source_url": "https://www.google.com/maps/reviews/data=!4m8!14m7!1m6!2m5!1sCi9DQUlRQUNvZENodHljRjlvT214S1YyNDVNamhRVGxkRE5rNVVNazUwYUZSUFRXYxAB!2m1!1s0x0:0x4c81e5d9412ac4b7!3m1!1s2@1:CAIQACodChtycF9oOmxKV245MjhQTldDNk5UMk50aFRPTWc%7C%7C?hl=en-US"
  },
  {
    "provider_name": "Removery (Sugar Land)",
    "location_city": "Sugar Land",
    "location_state": "TX",
    "method_used": "PicoWay",
    "review_text": "Staff at Sugar Land location is extremely knowledgeable and helpful throughout the process. Great service.",
    "star_rating": 5,
    "review_date": "3 weeks ago",
    "review_date_iso": "2026-04-02T18:38:30Z",
    "review_date_edited_iso": "2026-04-02T18:38:30Z",
    "reviewer_name": "Gloria E. Aguirre-Virola",
    "reviewer_local_guide": true,
    "verified_source": "Google",
    "_place_title": "Removery Tattoo Removal & Fading",
    "_place_id": "ChIJ8yqCOdvnQIYRt8QqQdnlgUw",
    "_scrape_mode": "full",
    "_scrape_date": "2026-04-28",
    "source_url": "https://www.google.com/maps/reviews/data=!4m8!14m7!1m6!2m5!1sCi9DQUlRQUNvZENodHljRjlvT21aa01XSmlORGhPVURsUVJGWkxNVlk1VlRFNVQzYxAB!2m1!1s0x0:0x4c81e5d9412ac4b7!3m1!1s2@1:CAIQACodChtycF9oOmZkMWJiNDhOUDlQRFZLMVY5VTE5T3c%7C%7C?hl=en-US"
  },
  {
    "provider_name": "Removery (Sugar Land)",
    "location_city": "Sugar Land",
    "location_state": "TX",
    "method_used": "PicoWay",
    "review_text": "Such an amazing opportunity to come across a very put together location with very nice people and the process is as smooth as possible thank you so much removery ❤️",
    "star_rating": 5,
    "review_date": "4 weeks ago",
    "review_date_iso": "2026-03-30T02:26:46Z",
    "review_date_edited_iso": "2026-03-30T02:26:46Z",
    "reviewer_name": "Heydee Bandzz",
    "reviewer_local_guide": true,
    "verified_source": "Google",
    "_place_title": "Removery Tattoo Removal & Fading",
    "_place_id": "ChIJ8yqCOdvnQIYRt8QqQdnlgUw",
    "_scrape_mode": "full",
    "_scrape_date": "2026-04-28",
    "source_url": "https://www.google.com/maps/reviews/data=!4m8!14m7!1m6!2m5!1sCi9DQUlRQUNvZENodHljRjlvT21oWFFuRnFSMHBPTkRaVmFrdFBRbWN0WmxKMmVVRRAB!2m1!1s0x0:0x4c81e5d9412ac4b7!3m1!1s2@1:CAIQACodChtycF9oOmhXQnFqR0pONDZVaktPQmctZlJ2eUE%7C%7C?hl=en-US"
  },
  {
    "provider_name": "Removery (Sugar Land)",
    "location_city": "Sugar Land",
    "location_state": "TX",
    "method_used": "PicoWay",
    "review_text": "",
    "star_rating": 5,
    "review_date": "Edited 4 weeks ago",
    "review_date_iso": "2023-04-29T14:28:54Z",
    "review_date_edited_iso": "2026-03-28T20:34:53Z",
    "reviewer_name": "Jairo Escobar",
    "reviewer_local_guide": true,
    "verified_source": "Google",
    "_place_title": "Removery Tattoo Removal & Fading",
    "_place_id": "ChIJ8yqCOdvnQIYRt8QqQdnlgUw",
    "_scrape_mode": "full",
    "_scrape_date": "2026-04-28",
    "source_url": "https://www.google.com/maps/reviews/data=!4m8!14m7!1m6!2m5!1sChdDSUhNMG9nS0VJQ0FnSURSaFk3aXJ3RRAB!2m1!1s0x0:0x4c81e5d9412ac4b7!3m1!1s2@1:CIHM0ogKEICAgIDRhY7irwE%7C%7C?hl=en-US"
  },
  {
    "provider_name": "Removery (Sugar Land)",
    "location_city": "Sugar Land",
    "location_state": "TX",
    "method_used": "PicoWay",
    "review_text": "So far the treatment has been great. The tattoo is fading and I have had no skin issues with my sensitive skin during the treatment. The ladies in the office are very sweet and easy to work with.",
    "star_rating": 5,
    "review_date": "a month ago",
    "review_date_iso": "2026-03-24T21:20:28Z",
    "review_date_edited_iso": "2026-03-24T21:20:28Z",
    "reviewer_name": "Christy Collins",
    "reviewer_local_guide": true,
    "verified_source": "Google",
    "_place_title": "Removery Tattoo Removal & Fading",
    "_place_id": "ChIJ8yqCOdvnQIYRt8QqQdnlgUw",
    "_scrape_mode": "full",
    "_scrape_date": "2026-04-28",
    "source_url": "https://www.google.com/maps/reviews/data=!4m8!14m7!1m6!2m5!1sCi9DQUlRQUNvZENodHljRjlvT21kMmN6ZHdUVnBWTmxkWFlYQmtjR0V3VGxGNFVVRRAB!2m1!1s0x0:0x4c81e5d9412ac4b7!3m1!1s2@1:CAIQACodChtycF9oOmd2czdwTVpVNldXYXBkcGEwTlF4UUE%7C%7C?hl=en"
  },
  {
    "provider_name": "Removery (Sugar Land)",
    "location_city": "Sugar Land",
    "location_state": "TX",
    "method_used": "PicoWay",
    "review_text": "Super friendly. Would recommend.",
    "star_rating": 5,
    "review_date": "a month ago",
    "review_date_iso": "2026-03-24T21:14:30Z",
    "review_date_edited_iso": "2026-03-24T21:14:30Z",
    "reviewer_name": "Kaylee Collins",
    "reviewer_local_guide": true,
    "verified_source": "Google",
    "_place_title": "Removery Tattoo Removal & Fading",
    "_place_id": "ChIJ8yqCOdvnQIYRt8QqQdnlgUw",
    "_scrape_mode": "full",
    "_scrape_date": "2026-04-28",
    "source_url": "https://www.google.com/maps/reviews/data=!4m8!14m7!1m6!2m5!1sCi9DQUlRQUNvZENodHljRjlvT2sxQmQydDRkVUprWjNSeWNETkxkak5zWTNOSlpVRRAB!2m1!1s0x0:0x4c81e5d9412ac4b7!3m1!1s2@1:CAIQACodChtycF9oOk1Bd2t4dUJkZ3RycDNLdjNsY3NJZUE%7C%7C?hl=en"
  },
  {
    "provider_name": "Removery (Sugar Land)",
    "location_city": "Sugar Land",
    "location_state": "TX",
    "method_used": "PicoWay",
    "review_text": "LOVE IT HERE THEY DO AN AMAZING JOB! Ive been doing my sessions for about a year now and I’m obsessed! Everyone is knowledgeable and will not steer you wrong!",
    "star_rating": 5,
    "review_date": "a month ago",
    "review_date_iso": "2026-03-24T21:13:34Z",
    "review_date_edited_iso": "2026-03-24T21:13:34Z",
    "reviewer_name": "Victoria q",
    "reviewer_local_guide": true,
    "verified_source": "Google",
    "_place_title": "Removery Tattoo Removal & Fading",
    "_place_id": "ChIJ8yqCOdvnQIYRt8QqQdnlgUw",
    "_scrape_mode": "full",
    "_scrape_date": "2026-04-28",
    "source_url": "https://www.google.com/maps/reviews/data=!4m8!14m7!1m6!2m5!1sCi9DQUlRQUNvZENodHljRjlvT2xNeVgwUXdTRlUwTW5OUmRrUlpUakp0VTNwNk1uYxAB!2m1!1s0x0:0x4c81e5d9412ac4b7!3m1!1s2@1:CAIQACodChtycF9oOlMyX0QwSFU0MnNRdkRZTjJtU3p6Mnc%7C%7C?hl=en"
  },
  {
    "provider_name": "Removery (Sugar Land)",
    "location_city": "Sugar Land",
    "location_state": "TX",
    "method_used": "PicoWay",
    "review_text": "I got their services 2 1/2 years ago.  I only  had 4 session back then the technician who did my sessions was phenomenal and the place seemed really busy at the time.  I was given a discount for my first 3 package price.  However, today, 2 1/2 years later I went back to the same Sugar Land location and was really disappointed.  Let me just say that I had called their 1-888 number and they tried to get ahold of someone at this location because I had questions about their pricing, etc.  They couldn't reach anyone and told me someone would call me back.  Well after and hour I still didn't hear back from anyone.  So I drove over to the physical location.  A Jasmine/Yasmine? was at the front desk, and the place was completely empty, no clients, no busy servicing, her phone didn't ring once while I was there, and she was completely lacking in any initiative to help me with trying to figure out about any discounts available for a returning customer and it was like pulling teeth trying to find out pricing from her.  She seemed bored with me, like I was just an annoyance.  When I asked if the same tech was there that worked on me over 2 years ago, she said no before I ever gave a name.  Then she proceeded to tell me that they had a complete change over of ALL personnel including the regional manager.  When I said, boy it seems slow today, she said \"no, we are actually very busy and have a ton of clients\".  Well, I saw none..LOL  Anyway, it was really a turn off and I decided to leave and go somewhere else.  As a potential customer I want someone excited to tell me about their services and costs, even if I am a returning customer.  I want someone to be excited that I walked through the door.  But what I got was a very ho hum, I am bored with you customer treatment.  I loved this place 2 1/2 years ago, but not today years later.  One other thing, she said their were zero discounts or special offers.  When I went down the street to one of their competitors I got an amazing discount on a 10 session package and was treated like they were excited I walked through the door and were anxious to show off their place and tell me about all their services and products.  Sorry Removery but you lost me as a customer for offering no discounts to a returning customer and lacking any enthusiasm or showing initiative to gain me as a customer.",
    "star_rating": 2,
    "review_date": "a month ago",
    "review_date_iso": "2026-03-24T19:37:56Z",
    "review_date_edited_iso": "2026-03-24T19:39:26Z",
    "reviewer_name": "Cat 52",
    "reviewer_local_guide": true,
    "verified_source": "Google",
    "_place_title": "Removery Tattoo Removal & Fading",
    "_place_id": "ChIJ8yqCOdvnQIYRt8QqQdnlgUw",
    "_scrape_mode": "full",
    "_scrape_date": "2026-04-28",
    "source_url": "https://www.google.com/maps/reviews/data=!4m8!14m7!1m6!2m5!1sCi9DQUlRQUNvZENodHljRjlvT25OemNYcEhRa1JHVW5VellWcFBjSEV3V0RCMFdXYxAB!2m1!1s0x0:0x4c81e5d9412ac4b7!3m1!1s2@1:CAIQACodChtycF9oOnNzcXpHQkRGUnUzYVpPcHEwWDB0WWc%7C%7C?hl=en"
  },
  {
    "provider_name": "Removery (Sugar Land)",
    "location_city": "Sugar Land",
    "location_state": "TX",
    "method_used": "PicoWay",
    "review_text": "I had a really great experience at this tattoo removal clinic. The staff was very professional, kind, and made me feel comfortable throughout the entire process. I was honestly expecting the pain to be much worse, but it was very manageable and not as bad as I thought it would be.\n\nThey took the time to explain everything to me, answer all my questions, and made sure I felt at ease before starting. You can tell they really care about their clients and do quality work.\n\nI’m very happy with my results so far and would definitely recommend them to anyone considering tattoo removal!",
    "star_rating": 5,
    "review_date": "a month ago",
    "review_date_iso": "2026-03-17T20:04:59Z",
    "review_date_edited_iso": "2026-03-17T20:04:59Z",
    "reviewer_name": "Katlin Orellana",
    "reviewer_local_guide": true,
    "verified_source": "Google",
    "_place_title": "Removery Tattoo Removal & Fading",
    "_place_id": "ChIJ8yqCOdvnQIYRt8QqQdnlgUw",
    "_scrape_mode": "full",
    "_scrape_date": "2026-04-28",
    "source_url": "https://www.google.com/maps/reviews/data=!4m8!14m7!1m6!2m5!1sCi9DQUlRQUNvZENodHljRjlvT2xNNVkwdDBSSGxLWXpCTFRFWmlTRjlsWmxSNU1uYxAB!2m1!1s0x0:0x4c81e5d9412ac4b7!3m1!1s2@1:CAIQACodChtycF9oOlM5Y0t0RHlKYzBLTEZiSF9lZlR5Mnc%7C%7C?hl=en"
  },
  {
    "provider_name": "Removery (Sugar Land)",
    "location_city": "Sugar Land",
    "location_state": "TX",
    "method_used": "PicoWay",
    "review_text": "From the jump, the whole staff was super informative and helpful with all my questions.\n\nGave me re assurance and multiple options to chose from including good finance options as a veteran. Very affordable if you’re serious about removing a tattoo.\n\n6 sessions in so far and there’s definitely good results. Thank you removery!",
    "star_rating": 5,
    "review_date": "a month ago",
    "review_date_iso": "2026-03-14T19:04:07Z",
    "review_date_edited_iso": "2026-03-14T19:04:07Z",
    "reviewer_name": "Jeremy Rodriguez",
    "reviewer_local_guide": true,
    "verified_source": "Google",
    "_place_title": "Removery Tattoo Removal & Fading",
    "_place_id": "ChIJ8yqCOdvnQIYRt8QqQdnlgUw",
    "_scrape_mode": "full",
    "_scrape_date": "2026-04-28",
    "source_url": "https://www.google.com/maps/reviews/data=!4m8!14m7!1m6!2m5!1sCi9DQUlRQUNvZENodHljRjlvT21WV1duVjJORXRGWldSR1ZtTkhNVkV6TUU1UVVYYxAB!2m1!1s0x0:0x4c81e5d9412ac4b7!3m1!1s2@1:CAIQACodChtycF9oOmVWWnV2NEtFZWRGVmNHMVEzME5QUXc%7C%7C?hl=en"
  },
  {
    "provider_name": "Removery (Sugar Land)",
    "location_city": "Sugar Land",
    "location_state": "TX",
    "method_used": "PicoWay",
    "review_text": "Very welcoming place. Both of the ladies are amazing. My tattoo removal tech makes everything go smooth.",
    "star_rating": 5,
    "review_date": "Edited a month ago",
    "review_date_iso": "2026-01-02T18:51:45Z",
    "review_date_edited_iso": "2026-03-13T19:08:36Z",
    "reviewer_name": "Laura Anaya-Baez",
    "reviewer_local_guide": true,
    "verified_source": "Google",
    "_place_title": "Removery Tattoo Removal & Fading",
    "_place_id": "ChIJ8yqCOdvnQIYRt8QqQdnlgUw",
    "_scrape_mode": "full",
    "_scrape_date": "2026-04-28",
    "source_url": "https://www.google.com/maps/reviews/data=!4m8!14m7!1m6!2m5!1sCi9DQUlRQUNvZENodHljRjlvT2t4UmRYWTFNbUZJYUVSVWFtRlNjbU54TlRCUFVtYxAB!2m1!1s0x0:0x4c81e5d9412ac4b7!3m1!1s2@1:CAIQACodChtycF9oOkxRdXY1MmFIaERUamFScmNxNTBPUmc%7C%7C?hl=en"
  },
  {
    "provider_name": "Removery (Sugar Land)",
    "location_city": "Sugar Land",
    "location_state": "TX",
    "method_used": "PicoWay",
    "review_text": "The ladies at the Sugar Land location are lovely. Great experience.",
    "star_rating": 5,
    "review_date": "a month ago",
    "review_date_iso": "2026-03-05T22:28:45Z",
    "review_date_edited_iso": "2026-03-05T22:28:45Z",
    "reviewer_name": "Mary Tamulevich",
    "reviewer_local_guide": true,
    "verified_source": "Google",
    "_place_title": "Removery Tattoo Removal & Fading",
    "_place_id": "ChIJ8yqCOdvnQIYRt8QqQdnlgUw",
    "_scrape_mode": "full",
    "_scrape_date": "2026-04-28",
    "source_url": "https://www.google.com/maps/reviews/data=!4m8!14m7!1m6!2m5!1sCi9DQUlRQUNvZENodHljRjlvT214d1IwZEVWekZ3YUdjNU4xTmhMVkZFYTFKYU0xRRAB!2m1!1s0x0:0x4c81e5d9412ac4b7!3m1!1s2@1:CAIQACodChtycF9oOmxwR0dEVzFwaGc5N1NhLVFEa1JaM1E%7C%7C?hl=en"
  },
  {
    "provider_name": "Removery (Sugar Land)",
    "location_city": "Sugar Land",
    "location_state": "TX",
    "method_used": "PicoWay",
    "review_text": "I had such an amazing experience at Removery today! I officially started my tattoo removal journey on multiple tattoos (both hands, foot, and two name tattoos), and I couldn’t be happier with my decision.\n\nYasmeen and Ashley were absolutely incredible. They were so kind, patient, and professional from the moment I walked in. They explained everything clearly, answered all of my questions, and made me feel completely comfortable and supported. The treatment itself was much more manageable than I expected, and they constantly checked in to make sure I was okay.\n\nWhat really made this experience even better was how transparent and helpful they were with pricing and financing. I was able to get an unlimited session package with 0% interest, which made such a big difference and gave me peace of mind knowing I can continue treatments until everything is fully gone.\n\nThis was such a meaningful step for me, and I’m truly grateful for how smooth and positive they made the entire process. I highly recommend Removery and especially Yasmeen and Ashley\nto anyone considering tattoo removal!",
    "star_rating": 5,
    "review_date": "2 months ago",
    "review_date_iso": "2026-02-25T23:30:15Z",
    "review_date_edited_iso": "2026-02-25T23:31:43Z",
    "reviewer_name": "Nadiah Khan",
    "reviewer_local_guide": true,
    "verified_source": "Google",
    "_place_title": "Removery Tattoo Removal & Fading",
    "_place_id": "ChIJ8yqCOdvnQIYRt8QqQdnlgUw",
    "_scrape_mode": "full",
    "_scrape_date": "2026-04-28",
    "source_url": "https://www.google.com/maps/reviews/data=!4m8!14m7!1m6!2m5!1sCi9DQUlRQUNvZENodHljRjlvT2pKa2QxUXRZVFY2WVRCc1NuRlZlRXBYVEd3NVlWRRAB!2m1!1s0x0:0x4c81e5d9412ac4b7!3m1!1s2@1:CAIQACodChtycF9oOjJkd1QtYTV6YTBsSnFVeEpXTGw5YVE%7C%7C?hl=en"
  },
  {
    "provider_name": "Removery (Sugar Land)",
    "location_city": "Sugar Land",
    "location_state": "TX",
    "method_used": "PicoWay",
    "review_text": "",
    "star_rating": 5,
    "review_date": "2 months ago",
    "review_date_iso": "2026-02-21T19:54:30Z",
    "review_date_edited_iso": "2026-02-21T19:54:30Z",
    "reviewer_name": "Ana Stuckett",
    "reviewer_local_guide": true,
    "verified_source": "Google",
    "_place_title": "Removery Tattoo Removal & Fading",
    "_place_id": "ChIJ8yqCOdvnQIYRt8QqQdnlgUw",
    "_scrape_mode": "full",
    "_scrape_date": "2026-04-28",
    "source_url": "https://www.google.com/maps/reviews/data=!4m8!14m7!1m6!2m5!1sCi9DQUlRQUNvZENodHljRjlvT2pWM1ptUkVTbTVyTVdwWlVuRjBNMmxpUW5kT01YYxAB!2m1!1s0x0:0x4c81e5d9412ac4b7!3m1!1s2@1:CAIQACodChtycF9oOjV3ZmRESm5rMWpZUnF0M2liQndOMXc%7C%7C?hl=en"
  },
  {
    "provider_name": "Removery (Sugar Land)",
    "location_city": "Sugar Land",
    "location_state": "TX",
    "method_used": "PicoWay",
    "review_text": "Great staff and great service.",
    "star_rating": 5,
    "review_date": "2 months ago",
    "review_date_iso": "2026-02-13T19:46:07Z",
    "review_date_edited_iso": "2026-02-13T19:46:07Z",
    "reviewer_name": "Jessica Kastner",
    "reviewer_local_guide": true,
    "verified_source": "Google",
    "_place_title": "Removery Tattoo Removal & Fading",
    "_place_id": "ChIJ8yqCOdvnQIYRt8QqQdnlgUw",
    "_scrape_mode": "full",
    "_scrape_date": "2026-04-28",
    "source_url": "https://www.google.com/maps/reviews/data=!4m8!14m7!1m6!2m5!1sCi9DQUlRQUNvZENodHljRjlvT2toeGJIbGhla1V5ZUZGdmEzZGtjRE5vUkZWb2QzYxAB!2m1!1s0x0:0x4c81e5d9412ac4b7!3m1!1s2@1:CAIQACodChtycF9oOkhxbHlhekUyeFFva3dkcDNoRFVod3c%7C%7C?hl=en"
  },
  {
    "provider_name": "Removery (Sugar Land)",
    "location_city": "Sugar Land",
    "location_state": "TX",
    "method_used": "PicoWay",
    "review_text": "Booked my consultation appointment online. Came in and filled out a few quick forms.\n\nYasmeen then spent over 30 minutes explaining the whole process, showed me examples of what to expect, and answered all my questions. I mentioned that I’ll be moving out of state soon, and she reassured me that all of my information and services transfers seamlessly to all their other locations.\n\nOnce I made the decision, I went next door for my first session with Ashley. She made sure I was comfortable and let me know exactly what to expect for my very first session. Just minutes later, I was leaving! In total I was there for 1 hour and 15 minutes (from filling out forms, to initial consultation, to treatment).\n\nBoth Yasmeen and Ashley explained everything thoroughly, step by step, without ever making me feel rushed. The whole experience felt professional, transparent, and genuine. Highly recommend!",
    "star_rating": 5,
    "review_date": "2 months ago",
    "review_date_iso": "2026-02-10T18:04:40Z",
    "review_date_edited_iso": "2026-02-10T18:04:40Z",
    "reviewer_name": "Ryan Tran",
    "reviewer_local_guide": true,
    "verified_source": "Google",
    "_place_title": "Removery Tattoo Removal & Fading",
    "_place_id": "ChIJ8yqCOdvnQIYRt8QqQdnlgUw",
    "_scrape_mode": "full",
    "_scrape_date": "2026-04-28",
    "source_url": "https://www.google.com/maps/reviews/data=!4m8!14m7!1m6!2m5!1sCi9DQUlRQUNvZENodHljRjlvT2pVMGFYRjNYMDFwWldoVU0wNVlaWGszVUcwd2MxRRAB!2m1!1s0x0:0x4c81e5d9412ac4b7!3m1!1s2@1:CAIQACodChtycF9oOjU0aXF3X01pZWhUM05YZXk3UG0wc1E%7C%7C?hl=en"
  },
  {
    "provider_name": "Removery (Sugar Land)",
    "location_city": "Sugar Land",
    "location_state": "TX",
    "method_used": "PicoWay",
    "review_text": "I’ve been coming to Removery for about a year and a half now for tattoo removal, and the results have been incredible. I have a large tattoo on my lower back, and I’ve seen so much improvement over time.\n\nMy current technician is absolutely amazing — professional, knowledgeable, patient, and genuinely caring. She always makes me feel comfortable and confident throughout the process. The consistency and care she brings to each session really shows in the results.\n\nI truly love this place and highly recommend it to anyone considering tattoo removal.",
    "star_rating": 5,
    "review_date": "2 months ago",
    "review_date_iso": "2026-02-07T17:31:14Z",
    "review_date_edited_iso": "2026-02-07T17:31:14Z",
    "reviewer_name": "Yolanda Sanchez",
    "reviewer_local_guide": true,
    "verified_source": "Google",
    "_place_title": "Removery Tattoo Removal & Fading",
    "_place_id": "ChIJ8yqCOdvnQIYRt8QqQdnlgUw",
    "_scrape_mode": "full",
    "_scrape_date": "2026-04-28",
    "source_url": "https://www.google.com/maps/reviews/data=!4m8!14m7!1m6!2m5!1sCi9DQUlRQUNvZENodHljRjlvT21oek5DMDFRM0owYjBJek1ITlJjVmhRYW5WU1JHYxAB!2m1!1s0x0:0x4c81e5d9412ac4b7!3m1!1s2@1:CAIQACodChtycF9oOmhzNC01Q3J0b0IzMHNRcVhQanVSRGc%7C%7C?hl=en"
  },
  {
    "provider_name": "Removery (Sugar Land)",
    "location_city": "Sugar Land",
    "location_state": "TX",
    "method_used": "PicoWay",
    "review_text": "Such a professional office, very well explained. Answered all my questions. From front of the clinic to back everyone was very patient and professional. Love their energy!",
    "star_rating": 5,
    "review_date": "2 months ago",
    "review_date_iso": "2026-01-29T21:20:14Z",
    "review_date_edited_iso": "2026-01-29T21:20:14Z",
    "reviewer_name": "Sandy Alviz",
    "reviewer_local_guide": true,
    "verified_source": "Google",
    "_place_title": "Removery Tattoo Removal & Fading",
    "_place_id": "ChIJ8yqCOdvnQIYRt8QqQdnlgUw",
    "_scrape_mode": "full",
    "_scrape_date": "2026-04-28",
    "source_url": "https://www.google.com/maps/reviews/data=!4m8!14m7!1m6!2m5!1sCi9DQUlRQUNvZENodHljRjlvT2toUVFrbzRXV0pmVW1oNE9XeDJNR0k0YVdNM0xWRRAB!2m1!1s0x0:0x4c81e5d9412ac4b7!3m1!1s2@1:CAIQACodChtycF9oOkhQQko4WWJfUmh4OWx2MGI4aWM3LVE%7C%7C?hl=en"
  },
  {
    "provider_name": "Removery (Sugar Land)",
    "location_city": "Sugar Land",
    "location_state": "TX",
    "method_used": "PicoWay",
    "review_text": "So thorough with the process and definitely made me feel more at ease ! Already seeing progress on one of my smaller tattoos.",
    "star_rating": 5,
    "review_date": "3 months ago",
    "review_date_iso": "2026-01-27T17:01:51Z",
    "review_date_edited_iso": "2026-01-27T17:01:51Z",
    "reviewer_name": "Emilie Elliott",
    "reviewer_local_guide": true,
    "verified_source": "Google",
    "_place_title": "Removery Tattoo Removal & Fading",
    "_place_id": "ChIJ8yqCOdvnQIYRt8QqQdnlgUw",
    "_scrape_mode": "full",
    "_scrape_date": "2026-04-28",
    "source_url": "https://www.google.com/maps/reviews/data=!4m8!14m7!1m6!2m5!1sCi9DQUlRQUNvZENodHljRjlvT2tzdFNVUmFkbGczYkVVMlEwNUlYM1JtV25WUFVIYxAB!2m1!1s0x0:0x4c81e5d9412ac4b7!3m1!1s2@1:CAIQACodChtycF9oOkstSURadlg3bEU2Q05IX3RmWnVPUHc%7C%7C?hl=en"
  },
  {
    "provider_name": "Removery (Sugar Land)",
    "location_city": "Sugar Land",
    "location_state": "TX",
    "method_used": "PicoWay",
    "review_text": "Buenos resultados hasta el momento tengo 5 secciones y todo va muy bien las chicas son geniales",
    "star_rating": 5,
    "review_date": "Edited 3 months ago",
    "review_date_iso": "2025-01-16T17:48:59Z",
    "review_date_edited_iso": "2026-01-23T18:45:50Z",
    "reviewer_name": "Fabricio Ulloa",
    "reviewer_local_guide": true,
    "verified_source": "Google",
    "_place_title": "Removery Tattoo Removal & Fading",
    "_place_id": "ChIJ8yqCOdvnQIYRt8QqQdnlgUw",
    "_scrape_mode": "full",
    "_scrape_date": "2026-04-28",
    "source_url": "https://www.google.com/maps/reviews/data=!4m8!14m7!1m6!2m5!1sChdDSUhNMG9nS0VJQ0FnSUNfZ1lIcHd3RRAB!2m1!1s0x0:0x4c81e5d9412ac4b7!3m1!1s2@1:CIHM0ogKEICAgIC_gYHpwwE%7C%7C?hl=en"
  },
  {
    "provider_name": "Removery (Sugar Land)",
    "location_city": "Sugar Land",
    "location_state": "TX",
    "method_used": "PicoWay",
    "review_text": "",
    "star_rating": 5,
    "review_date": "Edited 3 months ago",
    "review_date_iso": "2025-09-19T16:11:52Z",
    "review_date_edited_iso": "2026-01-23T18:28:06Z",
    "reviewer_name": "Laura Walker",
    "reviewer_local_guide": true,
    "verified_source": "Google",
    "_place_title": "Removery Tattoo Removal & Fading",
    "_place_id": "ChIJ8yqCOdvnQIYRt8QqQdnlgUw",
    "_scrape_mode": "full",
    "_scrape_date": "2026-04-28",
    "source_url": "https://www.google.com/maps/reviews/data=!4m8!14m7!1m6!2m5!1sCi9DQUlRQUNvZENodHljRjlvT2tnNVYycHRNM2t4V2tzeFJrOW1TMXBaTlU4NVgwRRAB!2m1!1s0x0:0x4c81e5d9412ac4b7!3m1!1s2@1:CAIQACodChtycF9oOkg5V2ptM3kxWksxRk9mS1pZNU85X0E%7C%7C?hl=en"
  },
  {
    "provider_name": "Removery (Sugar Land)",
    "location_city": "Sugar Land",
    "location_state": "TX",
    "method_used": "PicoWay",
    "review_text": "I have been going to Removery for a while now. When I first started my treatments I was a little nervous because I always heard the pain was worse than getting a tattoo. I just finished my 6th treatment and I will say the staff is kind and makes me feel as comfortable as possible. The appointment scheduling is accommodating. I see major results with my treatments. I would definitely recommend this place to anyone looking for tattoo removal.",
    "star_rating": 5,
    "review_date": "3 months ago",
    "review_date_iso": "2026-01-20T23:27:10Z",
    "review_date_edited_iso": "2026-01-20T23:27:10Z",
    "reviewer_name": "Hailey Bowie",
    "reviewer_local_guide": true,
    "verified_source": "Google",
    "_place_title": "Removery Tattoo Removal & Fading",
    "_place_id": "ChIJ8yqCOdvnQIYRt8QqQdnlgUw",
    "_scrape_mode": "full",
    "_scrape_date": "2026-04-28",
    "source_url": "https://www.google.com/maps/reviews/data=!4m8!14m7!1m6!2m5!1sCi9DQUlRQUNvZENodHljRjlvT2sxamR5MHRkV2hoZFRoblp6TnNVVFpQWkdGcFUwRRAB!2m1!1s0x0:0x4c81e5d9412ac4b7!3m1!1s2@1:CAIQACodChtycF9oOk1jdy0tdWhhdThnZzNsUTZPZGFpU0E%7C%7C?hl=en"
  },
  {
    "provider_name": "Removery (Sugar Land)",
    "location_city": "Sugar Land",
    "location_state": "TX",
    "method_used": "PicoWay",
    "review_text": "I went in for a consultation, and actually started my 1st treatment the same day. Everyone was very professional and friendly.  Everything was explained in detail, and all of my questions were answered fully. I was very pleased with my visit.",
    "star_rating": 5,
    "review_date": "3 months ago",
    "review_date_iso": "2026-01-15T21:31:47Z",
    "review_date_edited_iso": "2026-01-15T21:31:47Z",
    "reviewer_name": "Gena Hill-Dennis",
    "reviewer_local_guide": true,
    "verified_source": "Google",
    "_place_title": "Removery Tattoo Removal & Fading",
    "_place_id": "ChIJ8yqCOdvnQIYRt8QqQdnlgUw",
    "_scrape_mode": "full",
    "_scrape_date": "2026-04-28",
    "source_url": "https://www.google.com/maps/reviews/data=!4m8!14m7!1m6!2m5!1sCi9DQUlRQUNvZENodHljRjlvT21GQk9YWjJkWEU1YmpnMGFqaE1YMGRMUjI5eVNGRRAB!2m1!1s0x0:0x4c81e5d9412ac4b7!3m1!1s2@1:CAIQACodChtycF9oOmFBOXZ2dXE5bjg0ajhMX0dLR29ySFE%7C%7C?hl=en"
  },
  {
    "provider_name": "Removery (Sugar Land)",
    "location_city": "Sugar Land",
    "location_state": "TX",
    "method_used": "PicoWay",
    "review_text": "Best studio for tattoo removal ✨",
    "star_rating": 5,
    "review_date": "3 months ago",
    "review_date_iso": "2026-01-07T21:18:42Z",
    "review_date_edited_iso": "2026-01-07T21:18:42Z",
    "reviewer_name": "Anaan",
    "reviewer_local_guide": true,
    "verified_source": "Google",
    "_place_title": "Removery Tattoo Removal & Fading",
    "_place_id": "ChIJ8yqCOdvnQIYRt8QqQdnlgUw",
    "_scrape_mode": "full",
    "_scrape_date": "2026-04-28",
    "source_url": "https://www.google.com/maps/reviews/data=!4m8!14m7!1m6!2m5!1sCi9DQUlRQUNvZENodHljRjlvT25wdlZuaFFObHBNYkc1S2NEUmhSamRPWDFWd2FXYxAB!2m1!1s0x0:0x4c81e5d9412ac4b7!3m1!1s2@1:CAIQACodChtycF9oOnpvVnhQNlpMbG5KcDRhRjdOX1VwaWc%7C%7C?hl=en"
  },
  {
    "provider_name": "Removery (Sugar Land)",
    "location_city": "Sugar Land",
    "location_state": "TX",
    "method_used": "PicoWay",
    "review_text": "",
    "star_rating": 5,
    "review_date": "4 months ago",
    "review_date_iso": "2025-12-28T04:16:18Z",
    "review_date_edited_iso": "2025-12-28T04:16:18Z",
    "reviewer_name": "Khari White",
    "reviewer_local_guide": true,
    "verified_source": "Google",
    "_place_title": "Removery Tattoo Removal & Fading",
    "_place_id": "ChIJ8yqCOdvnQIYRt8QqQdnlgUw",
    "_scrape_mode": "full",
    "_scrape_date": "2026-04-28",
    "source_url": "https://www.google.com/maps/reviews/data=!4m8!14m7!1m6!2m5!1sCi9DQUlRQUNvZENodHljRjlvT2tGemExaDFWV1UxYzB4YVJXWk1WMmxHV214YVVGRRAB!2m1!1s0x0:0x4c81e5d9412ac4b7!3m1!1s2@1:CAIQACodChtycF9oOkFza1h1VWU1c0xaRWZMV2lGWmxaUFE%7C%7C?hl=en"
  },
  {
    "provider_name": "Removery (Sugar Land)",
    "location_city": "Sugar Land",
    "location_state": "TX",
    "method_used": "PicoWay",
    "review_text": "Thanks!!! Always great service always very clean and professional environment",
    "star_rating": 5,
    "review_date": "Edited 4 months ago",
    "review_date_iso": "2025-09-12T00:24:07Z",
    "review_date_edited_iso": "2025-12-10T21:04:07Z",
    "reviewer_name": "Alex Galvan",
    "reviewer_local_guide": true,
    "verified_source": "Google",
    "_place_title": "Removery Tattoo Removal & Fading",
    "_place_id": "ChIJ8yqCOdvnQIYRt8QqQdnlgUw",
    "_scrape_mode": "full",
    "_scrape_date": "2026-04-28",
    "source_url": "https://www.google.com/maps/reviews/data=!4m8!14m7!1m6!2m5!1sCi9DQUlRQUNvZENodHljRjlvT25nelpWcE1RM1pmWVVweVJUbFRkWGhRV0daelpVRRAB!2m1!1s0x0:0x4c81e5d9412ac4b7!3m1!1s2@1:CAIQACodChtycF9oOngzZVpMQ3ZfYUpyRTlTdXhQWGZzZUE%7C%7C?hl=en"
  },
  {
    "provider_name": "Removery (Sugar Land)",
    "location_city": "Sugar Land",
    "location_state": "TX",
    "method_used": "PicoWay",
    "review_text": "",
    "star_rating": 5,
    "review_date": "4 months ago",
    "review_date_iso": "2025-12-10T02:24:39Z",
    "review_date_edited_iso": "2025-12-10T02:24:39Z",
    "reviewer_name": "Lola Martinez",
    "reviewer_local_guide": true,
    "verified_source": "Google",
    "_place_title": "Removery Tattoo Removal & Fading",
    "_place_id": "ChIJ8yqCOdvnQIYRt8QqQdnlgUw",
    "_scrape_mode": "full",
    "_scrape_date": "2026-04-28",
    "source_url": "https://www.google.com/maps/reviews/data=!4m8!14m7!1m6!2m5!1sCi9DQUlRQUNvZENodHljRjlvT21kU05GRm1kVmRSWkRSQlRtOTZWSEI2YWpSdWIyYxAB!2m1!1s0x0:0x4c81e5d9412ac4b7!3m1!1s2@1:CAIQACodChtycF9oOmdSNFFmdVdRZDRBTm96VHB6ajRub2c%7C%7C?hl=en"
  },
  {
    "provider_name": "Removery (Sugar Land)",
    "location_city": "Sugar Land",
    "location_state": "TX",
    "method_used": "PicoWay",
    "review_text": "Ashley does a good job with my lasering and care within the process. My project is a challenge but im seeing a big difference  with patience  and endurance.  Thank you sm 🙏✨️🖤",
    "star_rating": 5,
    "review_date": "4 months ago",
    "review_date_iso": "2025-12-04T21:38:17Z",
    "review_date_edited_iso": "2025-12-04T21:38:17Z",
    "reviewer_name": "Chelsey Bolden",
    "reviewer_local_guide": true,
    "verified_source": "Google",
    "_place_title": "Removery Tattoo Removal & Fading",
    "_place_id": "ChIJ8yqCOdvnQIYRt8QqQdnlgUw",
    "_scrape_mode": "full",
    "_scrape_date": "2026-04-28",
    "source_url": "https://www.google.com/maps/reviews/data=!4m8!14m7!1m6!2m5!1sCi9DQUlRQUNvZENodHljRjlvT25sdVFWZzRZM3AwYUZrNE1HVXlYMHBEUTNjd2QyYxAB!2m1!1s0x0:0x4c81e5d9412ac4b7!3m1!1s2@1:CAIQACodChtycF9oOnluQVg4Y3p0aFk4MGUyX0pDQ3cwd2c%7C%7C?hl=en"
  },
  {
    "provider_name": "Removery (Sugar Land)",
    "location_city": "Sugar Land",
    "location_state": "TX",
    "method_used": "PicoWay",
    "review_text": "",
    "star_rating": 5,
    "review_date": "Edited 4 months ago",
    "review_date_iso": "2025-05-03T17:35:59Z",
    "review_date_edited_iso": "2025-12-02T18:19:09Z",
    "reviewer_name": "Marcus Ricks",
    "reviewer_local_guide": true,
    "verified_source": "Google",
    "_place_title": "Removery Tattoo Removal & Fading",
    "_place_id": "ChIJ8yqCOdvnQIYRt8QqQdnlgUw",
    "_scrape_mode": "full",
    "_scrape_date": "2026-04-28",
    "source_url": "https://www.google.com/maps/reviews/data=!4m8!14m7!1m6!2m5!1sChZDSUhNMG9nS0VJQ0FnTUNZdXJHY1NnEAE!2m1!1s0x0:0x4c81e5d9412ac4b7!3m1!1s2@1:CIHM0ogKEICAgMCYurGcSg%7C%7C?hl=en"
  },
  {
    "provider_name": "Removery (Sugar Land)",
    "location_city": "Sugar Land",
    "location_state": "TX",
    "method_used": "PicoWay",
    "review_text": "Ashley is always incredibly pleasant and welcoming every time I come in for my laser treatment. She takes great care to ensure the ice has done its job before we begin, which makes the experience much more comfortable. She's very informative and always takes the time to explain things clearly. I genuinely enjoy seeing Ashley at all my appointments—her professionalism and warmth make a big difference!",
    "star_rating": 5,
    "review_date": "Edited 5 months ago",
    "review_date_iso": "2024-08-06T22:51:34Z",
    "review_date_edited_iso": "2025-11-19T18:16:00Z",
    "reviewer_name": "Lorena S Fonseca",
    "reviewer_local_guide": true,
    "verified_source": "Google",
    "_place_title": "Removery Tattoo Removal & Fading",
    "_place_id": "ChIJ8yqCOdvnQIYRt8QqQdnlgUw",
    "_scrape_mode": "full",
    "_scrape_date": "2026-04-28",
    "source_url": "https://www.google.com/maps/reviews/data=!4m8!14m7!1m6!2m5!1sChZDSUhNMG9nS0VJQ0FnSURicWRXRUh3EAE!2m1!1s0x0:0x4c81e5d9412ac4b7!3m1!1s2@1:CIHM0ogKEICAgIDbqdWEHw%7C%7C?hl=en"
  },
  {
    "provider_name": "Removery (Sugar Land)",
    "location_city": "Sugar Land",
    "location_state": "TX",
    "method_used": "PicoWay",
    "review_text": "i’ve been going to Removery for over a year now and Ashley has been amazing every session. She’s polite, knows what’s she’s doing and is a very well communicator!",
    "star_rating": 5,
    "review_date": "5 months ago",
    "review_date_iso": "2025-11-18T22:17:01Z",
    "review_date_edited_iso": "2025-11-18T22:17:01Z",
    "reviewer_name": "Andrew Garcia",
    "reviewer_local_guide": true,
    "verified_source": "Google",
    "_place_title": "Removery Tattoo Removal & Fading",
    "_place_id": "ChIJ8yqCOdvnQIYRt8QqQdnlgUw",
    "_scrape_mode": "full",
    "_scrape_date": "2026-04-28",
    "source_url": "https://www.google.com/maps/reviews/data=!4m8!14m7!1m6!2m5!1sCi9DQUlRQUNvZENodHljRjlvT2twNFVVOW9NemMyTm5aTWJrcEZkMkpDUjNOUVgxRRAB!2m1!1s0x0:0x4c81e5d9412ac4b7!3m1!1s2@1:CAIQACodChtycF9oOkp4UU9oMzc2NnZMbkpFd2JCR3NQX1E%7C%7C?hl=en"
  },
  {
    "provider_name": "Removery (Sugar Land)",
    "location_city": "Sugar Land",
    "location_state": "TX",
    "method_used": "PicoWay",
    "review_text": "I had my first laser tattoo removal session yesterday, and Ashley was amazing! She explained everything clearly, checked in on me throughout the process, and made sure I was completely comfortable. Her professionalism and kindness really put me at ease. Highly recommend Ashley if you’re considering tattoo removal!",
    "star_rating": 5,
    "review_date": "5 months ago",
    "review_date_iso": "2025-11-15T18:52:11Z",
    "review_date_edited_iso": "2025-11-15T18:52:11Z",
    "reviewer_name": "Neida Martinez",
    "reviewer_local_guide": true,
    "verified_source": "Google",
    "_place_title": "Removery Tattoo Removal & Fading",
    "_place_id": "ChIJ8yqCOdvnQIYRt8QqQdnlgUw",
    "_scrape_mode": "full",
    "_scrape_date": "2026-04-28",
    "source_url": "https://www.google.com/maps/reviews/data=!4m8!14m7!1m6!2m5!1sCi9DQUlRQUNvZENodHljRjlvT2xoUFpVeERNbTAxVXpobVZVaHpRaTFCYTFWS1ZVRRAB!2m1!1s0x0:0x4c81e5d9412ac4b7!3m1!1s2@1:CAIQACodChtycF9oOlhPZUxDMm01UzhmVUhzQi1Ba1VKVUE%7C%7C?hl=en"
  },
  {
    "provider_name": "Removery (Sugar Land)",
    "location_city": "Sugar Land",
    "location_state": "TX",
    "method_used": "PicoWay",
    "review_text": "I ALWAYS have a good experience when I come for my appointments/treatments The staff is very helpful, caring,, knowledgeable and professional . My husband says he can see a difference!",
    "star_rating": 5,
    "review_date": "5 months ago",
    "review_date_iso": "2025-11-15T18:16:19Z",
    "review_date_edited_iso": "2025-11-15T18:16:19Z",
    "reviewer_name": "Josephine Pina",
    "reviewer_local_guide": true,
    "verified_source": "Google",
    "_place_title": "Removery Tattoo Removal & Fading",
    "_place_id": "ChIJ8yqCOdvnQIYRt8QqQdnlgUw",
    "_scrape_mode": "full",
    "_scrape_date": "2026-04-28",
    "source_url": "https://www.google.com/maps/reviews/data=!4m8!14m7!1m6!2m5!1sCi9DQUlRQUNvZENodHljRjlvT2tGa2JqVlRhVzR6Y0dGNVJIaFZTV2h4TFZSNmJHYxAB!2m1!1s0x0:0x4c81e5d9412ac4b7!3m1!1s2@1:CAIQACodChtycF9oOkFkbjVTaW4zcGF5RHhVSWhxLVR6bGc%7C%7C?hl=en"
  },
  {
    "provider_name": "Removery (Sugar Land)",
    "location_city": "Sugar Land",
    "location_state": "TX",
    "method_used": "PicoWay",
    "review_text": "",
    "star_rating": 5,
    "review_date": "Edited 5 months ago",
    "review_date_iso": "2023-10-03T16:06:05Z",
    "review_date_edited_iso": "2025-11-15T16:32:03Z",
    "reviewer_name": "Rosi A",
    "reviewer_local_guide": true,
    "verified_source": "Google",
    "_place_title": "Removery Tattoo Removal & Fading",
    "_place_id": "ChIJ8yqCOdvnQIYRt8QqQdnlgUw",
    "_scrape_mode": "full",
    "_scrape_date": "2026-04-28",
    "source_url": "https://www.google.com/maps/reviews/data=!4m8!14m7!1m6!2m5!1sChZDSUhNMG9nS0VJQ0FnSURaeVpxa2RBEAE!2m1!1s0x0:0x4c81e5d9412ac4b7!3m1!1s2@1:CIHM0ogKEICAgIDZyZqkdA%7C%7C?hl=en"
  },
  {
    "provider_name": "Removery (Sugar Land)",
    "location_city": "Sugar Land",
    "location_state": "TX",
    "method_used": "PicoWay",
    "review_text": "Ms. Yessmen who helped us is super terrific she was able to explain everything and walk us through the process very easily. She’s super wonderful!",
    "star_rating": 5,
    "review_date": "5 months ago",
    "review_date_iso": "2025-11-14T16:20:56Z",
    "review_date_edited_iso": "2025-11-14T16:20:56Z",
    "reviewer_name": "Ianna Blas",
    "reviewer_local_guide": true,
    "verified_source": "Google",
    "_place_title": "Removery Tattoo Removal & Fading",
    "_place_id": "ChIJ8yqCOdvnQIYRt8QqQdnlgUw",
    "_scrape_mode": "full",
    "_scrape_date": "2026-04-28",
    "source_url": "https://www.google.com/maps/reviews/data=!4m8!14m7!1m6!2m5!1sCi9DQUlRQUNvZENodHljRjlvT2treWNFRlNXVlYyV0ZOQlJFUm5UWGMxU1RFM04zYxAB!2m1!1s0x0:0x4c81e5d9412ac4b7!3m1!1s2@1:CAIQACodChtycF9oOkkycEFSWVV2WFNBRERnTXc1STE3N3c%7C%7C?hl=en"
  },
  {
    "provider_name": "Removery (Sugar Land)",
    "location_city": "Sugar Land",
    "location_state": "TX",
    "method_used": "PicoWay",
    "review_text": "I just had my first session at removery and I was WAY more scared than I was letting on. I was very anxious about the whole experience. Yasmeen and the laser tech made me feel super comfortable and they even helped me convince my boyfriend to be my emotional support during my first session. I look forward to continuing to work with them on this. Thanks!",
    "star_rating": 5,
    "review_date": "5 months ago",
    "review_date_iso": "2025-11-12T00:33:25Z",
    "review_date_edited_iso": "2025-11-12T00:33:25Z",
    "reviewer_name": "Salma Cuenca",
    "reviewer_local_guide": true,
    "verified_source": "Google",
    "_place_title": "Removery Tattoo Removal & Fading",
    "_place_id": "ChIJ8yqCOdvnQIYRt8QqQdnlgUw",
    "_scrape_mode": "full",
    "_scrape_date": "2026-04-28",
    "source_url": "https://www.google.com/maps/reviews/data=!4m8!14m7!1m6!2m5!1sCi9DQUlRQUNvZENodHljRjlvT25OdFpYZG1XbXROUjFSbFdsWjZZVGgwY2kxQlZGRRAB!2m1!1s0x0:0x4c81e5d9412ac4b7!3m1!1s2@1:CAIQACodChtycF9oOnNtZXdmWmtNR1RlWlZ6YTh0ci1BVFE%7C%7C?hl=en"
  },
  {
    "provider_name": "Removery (Sugar Land)",
    "location_city": "Sugar Land",
    "location_state": "TX",
    "method_used": "PicoWay",
    "review_text": "",
    "star_rating": 5,
    "review_date": "5 months ago",
    "review_date_iso": "2025-11-05T01:01:13Z",
    "review_date_edited_iso": "2025-11-05T01:01:13Z",
    "reviewer_name": "Lily Vasquez",
    "reviewer_local_guide": true,
    "verified_source": "Google",
    "_place_title": "Removery Tattoo Removal & Fading",
    "_place_id": "ChIJ8yqCOdvnQIYRt8QqQdnlgUw",
    "_scrape_mode": "full",
    "_scrape_date": "2026-04-28",
    "source_url": "https://www.google.com/maps/reviews/data=!4m8!14m7!1m6!2m5!1sCi9DQUlRQUNvZENodHljRjlvT21wMk1IaEpkMDEwVFVKcldGUlBXRXBUTW5KVmNWRRAB!2m1!1s0x0:0x4c81e5d9412ac4b7!3m1!1s2@1:CAIQACodChtycF9oOmp2MHhJd010TUJrWFRPWEpTMnJVcVE%7C%7C?hl=en"
  },
  {
    "provider_name": "Removery (Sugar Land)",
    "location_city": "Sugar Land",
    "location_state": "TX",
    "method_used": "PicoWay",
    "review_text": "",
    "star_rating": 5,
    "review_date": "5 months ago",
    "review_date_iso": "2025-11-05T00:51:12Z",
    "review_date_edited_iso": "2025-11-05T00:51:12Z",
    "reviewer_name": "C. Seals",
    "reviewer_local_guide": true,
    "verified_source": "Google",
    "_place_title": "Removery Tattoo Removal & Fading",
    "_place_id": "ChIJ8yqCOdvnQIYRt8QqQdnlgUw",
    "_scrape_mode": "full",
    "_scrape_date": "2026-04-28",
    "source_url": "https://www.google.com/maps/reviews/data=!4m8!14m7!1m6!2m5!1sCi9DQUlRQUNvZENodHljRjlvT2sxQ1VWcFlhekJwTVhJM05rbGhSbG96YVZGVVRrRRAB!2m1!1s0x0:0x4c81e5d9412ac4b7!3m1!1s2@1:CAIQACodChtycF9oOk1CUVpYazBpMXI3NklhRlozaVFUTkE%7C%7C?hl=en"
  },
  {
    "provider_name": "Removery (Sugar Land)",
    "location_city": "Sugar Land",
    "location_state": "TX",
    "method_used": "PicoWay",
    "review_text": "I highly recommend this place for transparent communication, reliable results, and very friendly staff! Both Yasmeen and Ashley were fantastic to deal with and took their time to run through the whole procedure, answering any questions I had along the way. The pricing was actually way better I expected and they do have some great financing options. The sensation is a little like getting popped with hot grease or a static shock, but if you can sit through a tattoo you can sit through this . I've only had one session so far but I can already see some of the ink breaking down. I'm excited to see how the results progress with more sessions. Really great experience! 10/10 for staff!",
    "star_rating": 5,
    "review_date": "6 months ago",
    "review_date_iso": "2025-10-23T01:16:47Z",
    "review_date_edited_iso": "2025-10-23T01:18:08Z",
    "reviewer_name": "Alli Scott",
    "reviewer_local_guide": true,
    "verified_source": "Google",
    "_place_title": "Removery Tattoo Removal & Fading",
    "_place_id": "ChIJ8yqCOdvnQIYRt8QqQdnlgUw",
    "_scrape_mode": "full",
    "_scrape_date": "2026-04-28",
    "source_url": "https://www.google.com/maps/reviews/data=!4m8!14m7!1m6!2m5!1sCi9DQUlRQUNvZENodHljRjlvT2pJMGRIQnFObDloUW1oRlRrSXRjVmMzY0ZreVkwRRAB!2m1!1s0x0:0x4c81e5d9412ac4b7!3m1!1s2@1:CAIQACodChtycF9oOjI0dHBqNl9hQmhFTkItcVc3cFkyY0E%7C%7C?hl=en"
  },
  {
    "provider_name": "Removery (Sugar Land)",
    "location_city": "Sugar Land",
    "location_state": "TX",
    "method_used": "PicoWay",
    "review_text": "",
    "star_rating": 5,
    "review_date": "6 months ago",
    "review_date_iso": "2025-10-22T22:56:15Z",
    "review_date_edited_iso": "2025-10-22T22:56:15Z",
    "reviewer_name": "Che'Kierah Washington",
    "reviewer_local_guide": true,
    "verified_source": "Google",
    "_place_title": "Removery Tattoo Removal & Fading",
    "_place_id": "ChIJ8yqCOdvnQIYRt8QqQdnlgUw",
    "_scrape_mode": "full",
    "_scrape_date": "2026-04-28",
    "source_url": "https://www.google.com/maps/reviews/data=!4m8!14m7!1m6!2m5!1sCi9DQUlRQUNvZENodHljRjlvT2tobGEwUlpiREE0UkZkd1ZFbG9aMjAyVlUxaFJFRRAB!2m1!1s0x0:0x4c81e5d9412ac4b7!3m1!1s2@1:CAIQACodChtycF9oOkhla0RZbDA4RFdwVEloZ202VU1hREE%7C%7C?hl=en"
  },
  {
    "provider_name": "Removery (Sugar Land)",
    "location_city": "Sugar Land",
    "location_state": "TX",
    "method_used": "PicoWay",
    "review_text": "The staff had me feeling very comfortable once expressing my concerns! I really appreciate their help and I look forward to the removal of my tattoo.",
    "star_rating": 5,
    "review_date": "6 months ago",
    "review_date_iso": "2025-10-15T17:58:26Z",
    "review_date_edited_iso": "2025-10-15T17:58:26Z",
    "reviewer_name": "Ghosted Flicks",
    "reviewer_local_guide": true,
    "verified_source": "Google",
    "_place_title": "Removery Tattoo Removal & Fading",
    "_place_id": "ChIJ8yqCOdvnQIYRt8QqQdnlgUw",
    "_scrape_mode": "full",
    "_scrape_date": "2026-04-28",
    "source_url": "https://www.google.com/maps/reviews/data=!4m8!14m7!1m6!2m5!1sCi9DQUlRQUNvZENodHljRjlvT21OTloweEJXV3BGTmt0VmVWRXpVelF0YUhabFNFRRAB!2m1!1s0x0:0x4c81e5d9412ac4b7!3m1!1s2@1:CAIQACodChtycF9oOmNNZ0xBWWpFNktVeVEzUzQtaHZlSEE%7C%7C?hl=en"
  },
  {
    "provider_name": "Removery (Sugar Land)",
    "location_city": "Sugar Land",
    "location_state": "TX",
    "method_used": "PicoWay",
    "review_text": "Very informative for a first visit. Can’t wait to see my results.",
    "star_rating": 5,
    "review_date": "6 months ago",
    "review_date_iso": "2025-10-07T18:10:08Z",
    "review_date_edited_iso": "2025-10-07T18:10:08Z",
    "reviewer_name": "TenTex",
    "reviewer_local_guide": true,
    "verified_source": "Google",
    "_place_title": "Removery Tattoo Removal & Fading",
    "_place_id": "ChIJ8yqCOdvnQIYRt8QqQdnlgUw",
    "_scrape_mode": "full",
    "_scrape_date": "2026-04-28",
    "source_url": "https://www.google.com/maps/reviews/data=!4m8!14m7!1m6!2m5!1sCi9DQUlRQUNvZENodHljRjlvT25FdFdYUlRjMjlQTm5ZMWFtaEhSVU5oVkRGNFVXYxAB!2m1!1s0x0:0x4c81e5d9412ac4b7!3m1!1s2@1:CAIQACodChtycF9oOnEtWXRTc29PNnY1amhHRUNhVDF4UWc%7C%7C?hl=en"
  },
  {
    "provider_name": "Removery (Sugar Land)",
    "location_city": "Sugar Land",
    "location_state": "TX",
    "method_used": "PicoWay",
    "review_text": "Thank You all, all do an awesome job, and I will definitely send you people who are interested in getting there tattoo removed. And again thank you for all you do.",
    "star_rating": 5,
    "review_date": "Edited 7 months ago",
    "review_date_iso": "2023-11-27T20:29:21Z",
    "review_date_edited_iso": "2025-09-24T20:22:17Z",
    "reviewer_name": "Lester Sanchez",
    "reviewer_local_guide": true,
    "verified_source": "Google",
    "_place_title": "Removery Tattoo Removal & Fading",
    "_place_id": "ChIJ8yqCOdvnQIYRt8QqQdnlgUw",
    "_scrape_mode": "full",
    "_scrape_date": "2026-04-28",
    "source_url": "https://www.google.com/maps/reviews/data=!4m8!14m7!1m6!2m5!1sChdDSUhNMG9nS0VJQ0FnSUNsMl9HXzhRRRAB!2m1!1s0x0:0x4c81e5d9412ac4b7!3m1!1s2@1:CIHM0ogKEICAgICl2_G_8QE%7C%7C?hl=en"
  },
  {
    "provider_name": "Removery (Sugar Land)",
    "location_city": "Sugar Land",
    "location_state": "TX",
    "method_used": "PicoWay",
    "review_text": "Great consultation and staff. Very informative and thorough about the whole process. Look forward to using them for my treatment.",
    "star_rating": 5,
    "review_date": "7 months ago",
    "review_date_iso": "2025-09-21T16:09:11Z",
    "review_date_edited_iso": "2025-09-21T16:09:11Z",
    "reviewer_name": "nayab Rangrej",
    "reviewer_local_guide": true,
    "verified_source": "Google",
    "_place_title": "Removery Tattoo Removal & Fading",
    "_place_id": "ChIJ8yqCOdvnQIYRt8QqQdnlgUw",
    "_scrape_mode": "full",
    "_scrape_date": "2026-04-28",
    "source_url": "https://www.google.com/maps/reviews/data=!4m8!14m7!1m6!2m5!1sCi9DQUlRQUNvZENodHljRjlvT2sxUldIaHJNaTF4TldFeE1EaE1WMTlVYXpodVkyYxAB!2m1!1s0x0:0x4c81e5d9412ac4b7!3m1!1s2@1:CAIQACodChtycF9oOk1RWHhrMi1xNWExMDhMV19UazhuY2c%7C%7C?hl=en"
  },
  {
    "provider_name": "Removery (Sugar Land)",
    "location_city": "Sugar Land",
    "location_state": "TX",
    "method_used": "PicoWay",
    "review_text": "Great service ashley n is a great tech she help me olot with my removal!!",
    "star_rating": 5,
    "review_date": "7 months ago",
    "review_date_iso": "2025-09-20T21:07:19Z",
    "review_date_edited_iso": "2025-09-20T21:07:19Z",
    "reviewer_name": "houstoner fo life",
    "reviewer_local_guide": true,
    "verified_source": "Google",
    "_place_title": "Removery Tattoo Removal & Fading",
    "_place_id": "ChIJ8yqCOdvnQIYRt8QqQdnlgUw",
    "_scrape_mode": "full",
    "_scrape_date": "2026-04-28",
    "source_url": "https://www.google.com/maps/reviews/data=!4m8!14m7!1m6!2m5!1sCi9DQUlRQUNvZENodHljRjlvT2pGalkzQk9aMmwzVW5WUk1HUjVia2RoVkdoR2EzYxAB!2m1!1s0x0:0x4c81e5d9412ac4b7!3m1!1s2@1:CAIQACodChtycF9oOjFjY3BOZ2l3UnVRMGR5bkdhVGhGa3c%7C%7C?hl=en"
  },
  {
    "provider_name": "Removery (Sugar Land)",
    "location_city": "Sugar Land",
    "location_state": "TX",
    "method_used": "PicoWay",
    "review_text": "Best experience. Consultation was excellent with Jasmine and Ashley did the removal tattooing on my brows and was awesome. I highly recommend.\nSusan",
    "star_rating": 5,
    "review_date": "Edited 7 months ago",
    "review_date_iso": "2025-04-24T21:18:27Z",
    "review_date_edited_iso": "2025-09-20T17:43:43Z",
    "reviewer_name": "Susan Sprague",
    "reviewer_local_guide": true,
    "verified_source": "Google",
    "_place_title": "Removery Tattoo Removal & Fading",
    "_place_id": "ChIJ8yqCOdvnQIYRt8QqQdnlgUw",
    "_scrape_mode": "full",
    "_scrape_date": "2026-04-28",
    "source_url": "https://www.google.com/maps/reviews/data=!4m8!14m7!1m6!2m5!1sChdDSUhNMG9nS0VJQ0FnTURvanAyQzN3RRAB!2m1!1s0x0:0x4c81e5d9412ac4b7!3m1!1s2@1:CIHM0ogKEICAgMDojp2C3wE%7C%7C?hl=en"
  }
]