[
  {
    "provider_name": "inkOUT",
    "location_city": "Draper",
    "location_state": "UT",
    "method_used": "TEPR",
    "review_text": "",
    "star_rating": 5,
    "review_date": "a week ago",
    "review_date_iso": "2026-04-16T16:41:31Z",
    "review_date_edited_iso": "2026-04-16T16:41:31Z",
    "reviewer_name": "Steven McGovern",
    "reviewer_local_guide": true,
    "verified_source": "Google",
    "_place_title": "Rejuvatek Aesthetics providing inkOUT®",
    "_place_id": "ChIJwZ1KoJ6HUocRpaZ0Pq0XQaU",
    "_scrape_mode": "full",
    "_scrape_date": "2026-04-24",
    "source_url": "https://www.google.com/maps/reviews/data=!4m8!14m7!1m6!2m5!1sCi9DQUlRQUNvZENodHljRjlvT201dk5HbFpiMk13TVdKMFpXdDJkRE42ZDJsaE1YYxAB!2m1!1s0x0:0xa54117ad3e74a6a5!3m1!1s2@1:CAIQACodChtycF9oOm5vNGlZb2MwMWJ0ZWt2dDN6d2lhMXc%7C%7C?hl=en-US",
    "pain_level": "unknown",
    "scarring_mentioned": "No",
    "sessions_completed": "unknown",
    "skin_type": "unknown",
    "use_case": "unknown",
    "result_rating": "Positive",
    "review_date_estimated": "2026-04-16",
    "review_date_label": "Apr 16, 2026 (verified from SerpAPI iso_date, last edited Apr 16, 2026)",
    "review_date_source": "verified_serpapi",
    "has_text": false,
    "text_note": "Rating only — no written review text. Excluded from text-based analysis.",
    "brand_name": "inkOUT",
    "multi_location_brand": true,
    "location_transition": false,
    "transition_note": null
  },
  {
    "provider_name": "inkOUT",
    "location_city": "Draper",
    "location_state": "UT",
    "method_used": "TEPR",
    "review_text": "Getting a tattoo removed is not fun, or easy, but Brittany has been really easy to work with and is fast, professional and friendly.",
    "star_rating": 5,
    "review_date": "Edited a week ago",
    "review_date_iso": "2025-11-30T00:54:59Z",
    "review_date_edited_iso": "2026-04-16T16:41:16Z",
    "reviewer_name": "Iown YU",
    "reviewer_local_guide": true,
    "verified_source": "Google",
    "_place_title": "Rejuvatek Aesthetics providing inkOUT®",
    "_place_id": "ChIJwZ1KoJ6HUocRpaZ0Pq0XQaU",
    "_scrape_mode": "full",
    "_scrape_date": "2026-04-24",
    "source_url": "https://www.google.com/maps/reviews/data=!4m8!14m7!1m6!2m5!1sCi9DQUlRQUNvZENodHljRjlvT2t0M1MwdFJYMWc1ZGw5d1EzcEZTamR4WVhCcmNtYxAB!2m1!1s0x0:0xa54117ad3e74a6a5!3m1!1s2@1:CAIQACodChtycF9oOkt3S0tRX1g5dl9wQ3pFSjdxYXBrcmc%7C%7C?hl=en-US",
    "pain_level": "unknown",
    "scarring_mentioned": "No",
    "sessions_completed": "unknown",
    "skin_type": "unknown",
    "use_case": "Complete",
    "result_rating": "Positive",
    "review_date_estimated": "2025-11-30",
    "review_date_label": "Nov 30, 2025 (verified from SerpAPI iso_date, last edited Apr 16, 2026)",
    "review_date_source": "verified_serpapi",
    "has_text": true,
    "text_note": null,
    "brand_name": "inkOUT",
    "multi_location_brand": true,
    "location_transition": false,
    "transition_note": null
  },
  {
    "provider_name": "inkOUT",
    "location_city": "Draper",
    "location_state": "UT",
    "method_used": "TEPR",
    "review_text": "Britney  is absolutely amazing.  She is very professional explaining and answering  any questions I may have.  I have one more treatment and would recommend Britney and the Draper location.",
    "star_rating": 5,
    "review_date": "Edited 2 weeks ago",
    "review_date_iso": "2025-08-21T17:12:10Z",
    "review_date_edited_iso": "2026-04-08T16:30:54Z",
    "reviewer_name": "Kristin T",
    "reviewer_local_guide": true,
    "verified_source": "Google",
    "_place_title": "Rejuvatek Aesthetics providing inkOUT®",
    "_place_id": "ChIJwZ1KoJ6HUocRpaZ0Pq0XQaU",
    "_scrape_mode": "full",
    "_scrape_date": "2026-04-24",
    "source_url": "https://www.google.com/maps/reviews/data=!4m8!14m7!1m6!2m5!1sCi9DQUlRQUNvZENodHljRjlvT2xKVVZITllWekF3UmkwdExXUTJTazgxT1V4amMwRRAB!2m1!1s0x0:0xa54117ad3e74a6a5!3m1!1s2@1:CAIQACodChtycF9oOlJUVHNYVzAwRi0tLWQ2Sk81OUxjc0E%7C%7C?hl=en-US",
    "pain_level": "unknown",
    "scarring_mentioned": "No",
    "sessions_completed": "unknown",
    "skin_type": "unknown",
    "use_case": "unknown",
    "result_rating": "Positive",
    "review_date_estimated": "2025-08-21",
    "review_date_label": "Aug 21, 2025 (verified from SerpAPI iso_date, last edited Apr 08, 2026)",
    "review_date_source": "verified_serpapi",
    "has_text": true,
    "text_note": null,
    "brand_name": "inkOUT",
    "multi_location_brand": true,
    "location_transition": false,
    "transition_note": null
  },
  {
    "provider_name": "inkOUT",
    "location_city": "Draper",
    "location_state": "UT",
    "method_used": "TEPR",
    "review_text": "The results speak for itself. I have had a few treatments and the tattoo is fading away,",
    "star_rating": 5,
    "review_date": "3 weeks ago",
    "review_date_iso": "2026-04-02T23:31:08Z",
    "review_date_edited_iso": "2026-04-02T23:31:08Z",
    "reviewer_name": "Teag Whiting",
    "reviewer_local_guide": true,
    "verified_source": "Google",
    "_place_title": "Rejuvatek Aesthetics providing inkOUT®",
    "_place_id": "ChIJwZ1KoJ6HUocRpaZ0Pq0XQaU",
    "_scrape_mode": "full",
    "_scrape_date": "2026-04-24",
    "source_url": "https://www.google.com/maps/reviews/data=!4m8!14m7!1m6!2m5!1sCi9DQUlRQUNvZENodHljRjlvT21SMU1uaEdXVTUxTlZoTE9YTTJNMk5TWlZCTVQyYxAB!2m1!1s0x0:0xa54117ad3e74a6a5!3m1!1s2@1:CAIQACodChtycF9oOmR1MnhGWU51NVhLOXM2M2NSZVBMT2c%7C%7C?hl=en-US",
    "pain_level": "unknown",
    "scarring_mentioned": "No",
    "sessions_completed": "unknown",
    "skin_type": "unknown",
    "use_case": "Complete",
    "result_rating": "Positive",
    "review_date_estimated": "2026-04-02",
    "review_date_label": "Apr 02, 2026 (verified from SerpAPI iso_date, last edited Apr 02, 2026)",
    "review_date_source": "verified_serpapi",
    "has_text": true,
    "text_note": null,
    "brand_name": "inkOUT",
    "multi_location_brand": true,
    "location_transition": false,
    "transition_note": null
  },
  {
    "provider_name": "inkOUT",
    "location_city": "Draper",
    "location_state": "UT",
    "method_used": "TEPR",
    "review_text": "Had a great consultation with Britney. She answered all my questions and made me feel really comfortable with the treatment process.",
    "star_rating": 5,
    "review_date": "a month ago",
    "review_date_iso": "2026-03-01T19:37:54Z",
    "review_date_edited_iso": "2026-03-01T19:37:54Z",
    "reviewer_name": "Taylor Lyle",
    "reviewer_local_guide": true,
    "verified_source": "Google",
    "_place_title": "Rejuvatek Aesthetics providing inkOUT®",
    "_place_id": "ChIJwZ1KoJ6HUocRpaZ0Pq0XQaU",
    "_scrape_mode": "full",
    "_scrape_date": "2026-04-24",
    "source_url": "https://www.google.com/maps/reviews/data=!4m8!14m7!1m6!2m5!1sCi9DQUlRQUNvZENodHljRjlvT2pKQ1luWlhNbFZUWkY5eVEyMXJaMEZPTlZCUWEyYxAB!2m1!1s0x0:0xa54117ad3e74a6a5!3m1!1s2@1:CAIQACodChtycF9oOjJCYnZXMlVTZF9yQ21rZ0FONVBQa2c%7C%7C?hl=en-US",
    "pain_level": "unknown",
    "scarring_mentioned": "No",
    "sessions_completed": "unknown",
    "skin_type": "unknown",
    "use_case": "unknown",
    "result_rating": "Neutral",
    "review_date_estimated": "2026-03-01",
    "review_date_label": "Mar 01, 2026 (verified from SerpAPI iso_date, last edited Mar 01, 2026)",
    "review_date_source": "verified_serpapi",
    "has_text": true,
    "text_note": null,
    "brand_name": "inkOUT",
    "multi_location_brand": true,
    "location_transition": false,
    "transition_note": null
  },
  {
    "provider_name": "inkOUT",
    "location_city": "Draper",
    "location_state": "UT",
    "method_used": "TEPR",
    "review_text": "Britney was fantastic, very professional and helpful.\nEverything is very clean and well kept.\nI will say the removal process was a little more painful than I expected (I thought it would be similar to getting the tattoo).\nI look forward to seeing the progress of my removal.",
    "star_rating": 5,
    "review_date": "3 months ago",
    "review_date_iso": "2026-01-16T02:03:29Z",
    "review_date_edited_iso": "2026-01-16T02:03:29Z",
    "reviewer_name": "Gina Zipp",
    "reviewer_local_guide": true,
    "verified_source": "Google",
    "_place_title": "Rejuvatek Aesthetics providing inkOUT®",
    "_place_id": "ChIJwZ1KoJ6HUocRpaZ0Pq0XQaU",
    "_scrape_mode": "full",
    "_scrape_date": "2026-04-24",
    "source_url": "https://www.google.com/maps/reviews/data=!4m8!14m7!1m6!2m5!1sCi9DQUlRQUNvZENodHljRjlvT2pCMVVXdFJTRk5GZVd0Nk9GSnlSMFpJZVV4d01rRRAB!2m1!1s0x0:0xa54117ad3e74a6a5!3m1!1s2@1:CAIQACodChtycF9oOjB1UWtRSFNFeWt6OFJyR0ZIeUxwMkE%7C%7C?hl=en-US",
    "pain_level": 4,
    "scarring_mentioned": "No",
    "sessions_completed": "unknown",
    "skin_type": "unknown",
    "use_case": "Complete",
    "result_rating": "Neutral",
    "review_date_estimated": "2026-01-16",
    "review_date_label": "Jan 16, 2026 (verified from SerpAPI iso_date, last edited Jan 16, 2026)",
    "review_date_source": "verified_serpapi",
    "has_text": true,
    "text_note": null,
    "brand_name": "inkOUT",
    "multi_location_brand": true,
    "location_transition": false,
    "transition_note": null
  },
  {
    "provider_name": "inkOUT",
    "location_city": "Draper",
    "location_state": "UT",
    "method_used": "TEPR",
    "review_text": "STAY AWAY!! I did two sessions in 2022 and I still have the SCARS! These people mutilated my body and should not be in business. I followed all of the aftercare instructions perfectly and now I will have to pay hundreds of dollars to try n fix what they did to me. I have had random people come up to me and tell me they also scarred from this treatment! Strangers come up to me everywhere I go and ask about my arm it is embarrassing!! Do not trust them! This photo is what it looks like now, I do not want anyone else to go through this.",
    "star_rating": 1,
    "review_date": "3 months ago",
    "review_date_iso": "2026-01-12T21:50:42Z",
    "review_date_edited_iso": "2026-01-12T22:00:56Z",
    "reviewer_name": "Emma Kondris",
    "reviewer_local_guide": true,
    "verified_source": "Google",
    "_place_title": "Rejuvatek Aesthetics providing inkOUT®",
    "_place_id": "ChIJwZ1KoJ6HUocRpaZ0Pq0XQaU",
    "_scrape_mode": "full",
    "_scrape_date": "2026-04-24",
    "source_url": "https://www.google.com/maps/reviews/data=!4m8!14m7!1m6!2m5!1sCi9DQUlRQUNvZENodHljRjlvT25wTFZsVTJlVFIzWmw4NWFVNU5XbXRzWkU5VGFuYxAB!2m1!1s0x0:0xa54117ad3e74a6a5!3m1!1s2@1:CAIQACodChtycF9oOnpLVlU2eTR3Zl85aU5NWmtsZE9Tanc%7C%7C?hl=en-US",
    "pain_level": "unknown",
    "scarring_mentioned": "Yes",
    "sessions_completed": 2,
    "skin_type": "unknown",
    "use_case": "unknown",
    "result_rating": "Negative",
    "review_date_estimated": "2026-01-12",
    "review_date_label": "Jan 12, 2026 (verified from SerpAPI iso_date, last edited Jan 12, 2026)",
    "review_date_source": "verified_serpapi",
    "has_text": true,
    "text_note": null,
    "brand_name": "inkOUT",
    "multi_location_brand": true,
    "location_transition": false,
    "transition_note": null
  },
  {
    "provider_name": "inkOUT",
    "location_city": "Draper",
    "location_state": "UT",
    "method_used": "TEPR",
    "review_text": "Absolutely horrible experience. A close family member went here for tattoo removal and was left with severe scarring despite following every single aftercare instruction exactly as directed.\n\nThis procedure was significantly more painful than professional laser removal, yet delivered far worse results. Instead of fading the tattoo, it caused lasting damage that now requires laser treatment to fix the harm done here.\n\nIf you’re considering tattoo removal, do yourself a favor and look elsewhere. Read the other reviews carefully and consult a licensed laser removal provider instead. This place caused permanent consequences that could have been avoided.",
    "star_rating": 1,
    "review_date": "Edited 3 months ago",
    "review_date_iso": "2025-02-13T00:01:34Z",
    "review_date_edited_iso": "2026-01-12T21:47:54Z",
    "reviewer_name": "Maddie Bodily",
    "reviewer_local_guide": true,
    "verified_source": "Google",
    "_place_title": "Rejuvatek Aesthetics providing inkOUT®",
    "_place_id": "ChIJwZ1KoJ6HUocRpaZ0Pq0XQaU",
    "_scrape_mode": "full",
    "_scrape_date": "2026-04-24",
    "source_url": "https://www.google.com/maps/reviews/data=!4m8!14m7!1m6!2m5!1sChZDSUhNMG9nS0VJQ0FnTURBMy1ub1F3EAE!2m1!1s0x0:0xa54117ad3e74a6a5!3m1!1s2@1:CIHM0ogKEICAgMDA3-noQw%7C%7C?hl=en-US",
    "pain_level": 4,
    "scarring_mentioned": "Yes",
    "sessions_completed": "unknown",
    "skin_type": "unknown",
    "use_case": "Complete",
    "result_rating": "Negative",
    "review_date_estimated": "2025-02-13",
    "review_date_label": "Feb 13, 2025 (verified from SerpAPI iso_date, last edited Jan 12, 2026)",
    "review_date_source": "verified_serpapi",
    "has_text": true,
    "text_note": null,
    "brand_name": "inkOUT",
    "multi_location_brand": true,
    "location_transition": false,
    "transition_note": null
  },
  {
    "provider_name": "inkOUT",
    "location_city": "Draper",
    "location_state": "UT",
    "method_used": "TEPR",
    "review_text": "AVOID TATT2AWAY. My first and only session was Spring 2022. After proper aftercare and nearly four years later, the ink is mostly gone in the treated spots but I am also left with some hypertrophic scars from the procedure. If I were to continue with the removal process for the entire tattoo, I would choose laser or some other method, especially since its on my finger which has more sensitive and thinner skin more prone to scarring. Overall not impressed with the long-term results and wish I did more research before spending my money here. (The last photo was taken April 22, 2022, sometime after the procedure, the first two photos are fully healed December 2025)",
    "star_rating": 1,
    "review_date": "4 months ago",
    "review_date_iso": "2025-12-23T17:46:44Z",
    "review_date_edited_iso": "2025-12-24T15:16:09Z",
    "reviewer_name": "Ellie Cat",
    "reviewer_local_guide": true,
    "verified_source": "Google",
    "_place_title": "Rejuvatek Aesthetics providing inkOUT®",
    "_place_id": "ChIJwZ1KoJ6HUocRpaZ0Pq0XQaU",
    "_scrape_mode": "full",
    "_scrape_date": "2026-04-24",
    "source_url": "https://www.google.com/maps/reviews/data=!4m8!14m7!1m6!2m5!1sCi9DQUlRQUNvZENodHljRjlvT21zNFV6QmFOa3QyTms1TlltOXZiMGhRWWpCRFgyYxAB!2m1!1s0x0:0xa54117ad3e74a6a5!3m1!1s2@1:CAIQACodChtycF9oOms4UzBaNkt2Nk5NYm9vb0hQYjBDX2c%7C%7C?hl=en",
    "pain_level": "unknown",
    "scarring_mentioned": "Yes",
    "sessions_completed": 1,
    "skin_type": "unknown",
    "use_case": "Complete",
    "result_rating": "Negative",
    "review_date_estimated": "2025-12-23",
    "review_date_label": "Dec 23, 2025 (verified from SerpAPI iso_date, last edited Dec 24, 2025)",
    "review_date_source": "verified_serpapi",
    "has_text": true,
    "text_note": null,
    "brand_name": "inkOUT",
    "multi_location_brand": true,
    "location_transition": false,
    "transition_note": null
  },
  {
    "provider_name": "inkOUT",
    "location_city": "Draper",
    "location_state": "UT",
    "method_used": "TEPR",
    "review_text": "I regret going to Tatt2away more than getting the original tattoo. They mutilate you, end of story.",
    "star_rating": 1,
    "review_date": "4 months ago",
    "review_date_iso": "2025-12-09T00:58:45Z",
    "review_date_edited_iso": "2025-12-09T00:58:45Z",
    "reviewer_name": "connor weiss",
    "reviewer_local_guide": true,
    "verified_source": "Google",
    "_place_title": "Rejuvatek Aesthetics providing inkOUT®",
    "_place_id": "ChIJwZ1KoJ6HUocRpaZ0Pq0XQaU",
    "_scrape_mode": "full",
    "_scrape_date": "2026-04-24",
    "source_url": "https://www.google.com/maps/reviews/data=!4m8!14m7!1m6!2m5!1sCi9DQUlRQUNvZENodHljRjlvT21GV2NrRlNkRVpqZEd4MFpYQm5SSGh0T1ZVd1QyYxAB!2m1!1s0x0:0xa54117ad3e74a6a5!3m1!1s2@1:CAIQACodChtycF9oOmFWckFSdEZjdGx0ZXBnRHhtOVUwT2c%7C%7C?hl=en",
    "pain_level": "unknown",
    "scarring_mentioned": "Yes",
    "sessions_completed": "unknown",
    "skin_type": "unknown",
    "use_case": "unknown",
    "result_rating": "Negative",
    "review_date_estimated": "2025-12-09",
    "review_date_label": "Dec 09, 2025 (verified from SerpAPI iso_date, last edited Dec 09, 2025)",
    "review_date_source": "verified_serpapi",
    "has_text": true,
    "text_note": null,
    "brand_name": "inkOUT",
    "multi_location_brand": true,
    "location_transition": false,
    "transition_note": null
  },
  {
    "provider_name": "inkOUT",
    "location_city": "Draper",
    "location_state": "UT",
    "method_used": "TEPR",
    "review_text": "It’s always a lovely experience with Jazz and Britney. They both offer such a warm and welcoming environment. I’m so pleased with the results of my tattoo removal so far, and would recommend them to anyone looking into tattoo removal!",
    "star_rating": 5,
    "review_date": "4 months ago",
    "review_date_iso": "2025-12-05T17:09:24Z",
    "review_date_edited_iso": "2025-12-05T17:09:24Z",
    "reviewer_name": "Carson Pettingill",
    "reviewer_local_guide": true,
    "verified_source": "Google",
    "_place_title": "Rejuvatek Aesthetics providing inkOUT®",
    "_place_id": "ChIJwZ1KoJ6HUocRpaZ0Pq0XQaU",
    "_scrape_mode": "full",
    "_scrape_date": "2026-04-24",
    "source_url": "https://www.google.com/maps/reviews/data=!4m8!14m7!1m6!2m5!1sCi9DQUlRQUNvZENodHljRjlvT2tjMlltSlliV1ZpT1RZeVR6Tm1hRU5GVERGRWRsRRAB!2m1!1s0x0:0xa54117ad3e74a6a5!3m1!1s2@1:CAIQACodChtycF9oOkc2YmJYbWViOTYyTzNmaENFTDFEdlE%7C%7C?hl=en",
    "pain_level": "unknown",
    "scarring_mentioned": "No",
    "sessions_completed": "unknown",
    "skin_type": "unknown",
    "use_case": "Complete",
    "result_rating": "Positive",
    "review_date_estimated": "2025-12-05",
    "review_date_label": "Dec 05, 2025 (verified from SerpAPI iso_date, last edited Dec 05, 2025)",
    "review_date_source": "verified_serpapi",
    "has_text": true,
    "text_note": null,
    "brand_name": "inkOUT",
    "multi_location_brand": true,
    "location_transition": false,
    "transition_note": null
  },
  {
    "provider_name": "inkOUT",
    "location_city": "Draper",
    "location_state": "UT",
    "method_used": "TEPR",
    "review_text": "Brittney, the current Draper technician, is great! This technology is much more streamlined, effective, and therapeutic for the skin than traditional laser.",
    "star_rating": 4,
    "review_date": "6 months ago",
    "review_date_iso": "2025-10-03T17:14:14Z",
    "review_date_edited_iso": "2025-10-03T17:14:14Z",
    "reviewer_name": "Jordan Robert",
    "reviewer_local_guide": true,
    "verified_source": "Google",
    "_place_title": "Rejuvatek Aesthetics providing inkOUT®",
    "_place_id": "ChIJwZ1KoJ6HUocRpaZ0Pq0XQaU",
    "_scrape_mode": "full",
    "_scrape_date": "2026-04-24",
    "source_url": "https://www.google.com/maps/reviews/data=!4m8!14m7!1m6!2m5!1sCi9DQUlRQUNvZENodHljRjlvT21sNVZIQklZbkJRZFZFNVdEWkZUMHhXUjFWVlRYYxAB!2m1!1s0x0:0xa54117ad3e74a6a5!3m1!1s2@1:CAIQACodChtycF9oOml5VHBIYnBQdVE5WDZFT0xWR1VVTXc%7C%7C?hl=en",
    "pain_level": "unknown",
    "scarring_mentioned": "No",
    "sessions_completed": "unknown",
    "skin_type": "unknown",
    "use_case": "unknown",
    "result_rating": "Positive",
    "review_date_estimated": "2025-10-03",
    "review_date_label": "Oct 03, 2025 (verified from SerpAPI iso_date, last edited Oct 03, 2025)",
    "review_date_source": "verified_serpapi",
    "has_text": true,
    "text_note": null,
    "brand_name": "inkOUT",
    "multi_location_brand": true,
    "location_transition": false,
    "transition_note": null
  },
  {
    "provider_name": "inkOUT",
    "location_city": "Draper",
    "location_state": "UT",
    "method_used": "TEPR",
    "review_text": "Great experience! Very friendly!",
    "star_rating": 5,
    "review_date": "8 months ago",
    "review_date_iso": "2025-08-21T14:28:43Z",
    "review_date_edited_iso": "2025-08-21T14:28:43Z",
    "reviewer_name": "Arturo Martinez",
    "reviewer_local_guide": true,
    "verified_source": "Google",
    "_place_title": "Rejuvatek Aesthetics providing inkOUT®",
    "_place_id": "ChIJwZ1KoJ6HUocRpaZ0Pq0XQaU",
    "_scrape_mode": "full",
    "_scrape_date": "2026-04-24",
    "source_url": "https://www.google.com/maps/reviews/data=!4m8!14m7!1m6!2m5!1sCi9DQUlRQUNvZENodHljRjlvT2tObmFHZEhOMFo0WW5WalVWRmpWRnBMTjA5VlJIYxAB!2m1!1s0x0:0xa54117ad3e74a6a5!3m1!1s2@1:CAIQACodChtycF9oOkNnaGdHN0Z4YnVjUVFjVFpLN09VRHc%7C%7C?hl=en",
    "pain_level": "unknown",
    "scarring_mentioned": "No",
    "sessions_completed": "unknown",
    "skin_type": "unknown",
    "use_case": "unknown",
    "result_rating": "Positive",
    "review_date_estimated": "2025-08-21",
    "review_date_label": "Aug 21, 2025 (verified from SerpAPI iso_date, last edited Aug 21, 2025)",
    "review_date_source": "verified_serpapi",
    "has_text": true,
    "text_note": null,
    "brand_name": "inkOUT",
    "multi_location_brand": true,
    "location_transition": false,
    "transition_note": null
  },
  {
    "provider_name": "inkOUT",
    "location_city": "Draper",
    "location_state": "UT",
    "method_used": "TEPR",
    "review_text": "Britney was very helpful in my tattoo removal process. she also was able to answer questions about remaining payments I had.",
    "star_rating": 5,
    "review_date": "8 months ago",
    "review_date_iso": "2025-08-12T23:47:50Z",
    "review_date_edited_iso": "2025-08-12T23:47:50Z",
    "reviewer_name": "Siokapesi Hafoka",
    "reviewer_local_guide": true,
    "verified_source": "Google",
    "_place_title": "Rejuvatek Aesthetics providing inkOUT®",
    "_place_id": "ChIJwZ1KoJ6HUocRpaZ0Pq0XQaU",
    "_scrape_mode": "full",
    "_scrape_date": "2026-04-24",
    "source_url": "https://www.google.com/maps/reviews/data=!4m8!14m7!1m6!2m5!1sCi9DQUlRQUNvZENodHljRjlvT21oMlVWaHdjR2MwU2xwRFJXTTFNa2h3TTJ0MmRXYxAB!2m1!1s0x0:0xa54117ad3e74a6a5!3m1!1s2@1:CAIQACodChtycF9oOmh2UVhwcGc0SlpDRWM1MkhwM2t2dWc%7C%7C?hl=en",
    "pain_level": "unknown",
    "scarring_mentioned": "No",
    "sessions_completed": "unknown",
    "skin_type": "unknown",
    "use_case": "unknown",
    "result_rating": "Neutral",
    "review_date_estimated": "2025-08-12",
    "review_date_label": "Aug 12, 2025 (verified from SerpAPI iso_date, last edited Aug 12, 2025)",
    "review_date_source": "verified_serpapi",
    "has_text": true,
    "text_note": null,
    "brand_name": "inkOUT",
    "multi_location_brand": true,
    "location_transition": false,
    "transition_note": null
  },
  {
    "provider_name": "inkOUT",
    "location_city": "Draper",
    "location_state": "UT",
    "method_used": "TEPR",
    "review_text": "I had my 3rd treatment with Britney P yesterday. She was so kind and made sure I was comfortable, my appointment was a breeze with minimal pain. I think the important thing to remember is that this process takes time, but it works. Seeing my ink disappear has been so healing for me. Thanks Britney and Tatt2away!",
    "star_rating": 5,
    "review_date": "Edited 8 months ago",
    "review_date_iso": "2024-11-02T22:29:43Z",
    "review_date_edited_iso": "2025-08-07T16:32:33Z",
    "reviewer_name": "Lauren Broadhead",
    "reviewer_local_guide": true,
    "verified_source": "Google",
    "_place_title": "Rejuvatek Aesthetics providing inkOUT®",
    "_place_id": "ChIJwZ1KoJ6HUocRpaZ0Pq0XQaU",
    "_scrape_mode": "full",
    "_scrape_date": "2026-04-24",
    "source_url": "https://www.google.com/maps/reviews/data=!4m8!14m7!1m6!2m5!1sChdDSUhNMG9nS0VJQ0FnSUMzeEsyU21nRRAB!2m1!1s0x0:0xa54117ad3e74a6a5!3m1!1s2@1:CIHM0ogKEICAgIC3xK2SmgE%7C%7C?hl=en",
    "pain_level": 2,
    "scarring_mentioned": "No",
    "sessions_completed": 3,
    "skin_type": "unknown",
    "use_case": "Complete",
    "result_rating": "Positive",
    "review_date_estimated": "2024-11-02",
    "review_date_label": "Nov 02, 2024 (verified from SerpAPI iso_date, last edited Aug 07, 2025)",
    "review_date_source": "verified_serpapi",
    "has_text": true,
    "text_note": null,
    "brand_name": "inkOUT",
    "multi_location_brand": true,
    "location_transition": false,
    "transition_note": null
  },
  {
    "provider_name": "inkOUT",
    "location_city": "Draper",
    "location_state": "UT",
    "method_used": "TEPR",
    "review_text": "Finished the first session with Britney. She was on time and very professional. Despite my willingness to do whatever was asked of me, Britney was extremely attentive and helpful. I highly recommend this tattoo removal site!",
    "star_rating": 5,
    "review_date": "8 months ago",
    "review_date_iso": "2025-08-02T22:06:41Z",
    "review_date_edited_iso": "2025-08-02T22:06:41Z",
    "reviewer_name": "Mitch Baker",
    "reviewer_local_guide": true,
    "verified_source": "Google",
    "_place_title": "Rejuvatek Aesthetics providing inkOUT®",
    "_place_id": "ChIJwZ1KoJ6HUocRpaZ0Pq0XQaU",
    "_scrape_mode": "full",
    "_scrape_date": "2026-04-24",
    "source_url": "https://www.google.com/maps/reviews/data=!4m8!14m7!1m6!2m5!1sCi9DQUlRQUNvZENodHljRjlvT2xsVWFGTkNObGx1ZFZOTmFYSkpVMXBSVW1aYU4zYxAB!2m1!1s0x0:0xa54117ad3e74a6a5!3m1!1s2@1:CAIQACodChtycF9oOllUaFNCNlludVNNaXJJU1pRUmZaN3c%7C%7C?hl=en",
    "pain_level": "unknown",
    "scarring_mentioned": "No",
    "sessions_completed": 1,
    "skin_type": "unknown",
    "use_case": "unknown",
    "result_rating": "Neutral",
    "review_date_estimated": "2025-08-02",
    "review_date_label": "Aug 02, 2025 (verified from SerpAPI iso_date, last edited Aug 02, 2025)",
    "review_date_source": "verified_serpapi",
    "has_text": true,
    "text_note": null,
    "brand_name": "inkOUT",
    "multi_location_brand": true,
    "location_transition": false,
    "transition_note": null
  },
  {
    "provider_name": "inkOUT",
    "location_city": "Draper",
    "location_state": "UT",
    "method_used": "TEPR",
    "review_text": "I just had my 4th session with Britney Pham and I am very happy with how things are going! Britney made me feel very comfortable and made sure all of my questions were answered before I left. I’m very pleased!",
    "star_rating": 5,
    "review_date": "9 months ago",
    "review_date_iso": "2025-07-09T19:25:47Z",
    "review_date_edited_iso": "2025-07-09T19:25:47Z",
    "reviewer_name": "Mikaele Shields",
    "reviewer_local_guide": true,
    "verified_source": "Google",
    "_place_title": "Rejuvatek Aesthetics providing inkOUT®",
    "_place_id": "ChIJwZ1KoJ6HUocRpaZ0Pq0XQaU",
    "_scrape_mode": "full",
    "_scrape_date": "2026-04-24",
    "source_url": "https://www.google.com/maps/reviews/data=!4m8!14m7!1m6!2m5!1sCi9DQUlRQUNvZENodHljRjlvT21SMmVXcHROV1JWZG1RNVVVZzFWVjlxV1dKTmNsRRAB!2m1!1s0x0:0xa54117ad3e74a6a5!3m1!1s2@1:CAIQACodChtycF9oOmR2eWptNWRVdmQ5UUg1VV9qWWJNclE%7C%7C?hl=en",
    "pain_level": "unknown",
    "scarring_mentioned": "No",
    "sessions_completed": 4,
    "skin_type": "unknown",
    "use_case": "unknown",
    "result_rating": "Positive",
    "review_date_estimated": "2025-07-09",
    "review_date_label": "Jul 09, 2025 (verified from SerpAPI iso_date, last edited Jul 09, 2025)",
    "review_date_source": "verified_serpapi",
    "has_text": true,
    "text_note": null,
    "brand_name": "inkOUT",
    "multi_location_brand": true,
    "location_transition": false,
    "transition_note": null
  },
  {
    "provider_name": "inkOUT",
    "location_city": "Draper",
    "location_state": "UT",
    "method_used": "TEPR",
    "review_text": "Nice, comfortable space, explained aftercare in simple terms, good attention to detail.",
    "star_rating": 5,
    "review_date": "9 months ago",
    "review_date_iso": "2025-07-05T20:41:10Z",
    "review_date_edited_iso": "2025-07-05T20:41:10Z",
    "reviewer_name": "Robert St. Lezin",
    "reviewer_local_guide": true,
    "verified_source": "Google",
    "_place_title": "Rejuvatek Aesthetics providing inkOUT®",
    "_place_id": "ChIJwZ1KoJ6HUocRpaZ0Pq0XQaU",
    "_scrape_mode": "full",
    "_scrape_date": "2026-04-24",
    "source_url": "https://www.google.com/maps/reviews/data=!4m8!14m7!1m6!2m5!1sCi9DQUlRQUNvZENodHljRjlvT2t4aVVteDZXbE4xY3pSTE5qbGZiSGRrU1ZkbFUwRRAB!2m1!1s0x0:0xa54117ad3e74a6a5!3m1!1s2@1:CAIQACodChtycF9oOkxiUmx6WlN1czRLNjlfbHdkSVdlU0E%7C%7C?hl=en",
    "pain_level": "unknown",
    "scarring_mentioned": "No",
    "sessions_completed": "unknown",
    "skin_type": "unknown",
    "use_case": "unknown",
    "result_rating": "Neutral",
    "review_date_estimated": "2025-07-05",
    "review_date_label": "Jul 05, 2025 (verified from SerpAPI iso_date, last edited Jul 05, 2025)",
    "review_date_source": "verified_serpapi",
    "has_text": true,
    "text_note": null,
    "brand_name": "inkOUT",
    "multi_location_brand": true,
    "location_transition": false,
    "transition_note": null
  },
  {
    "provider_name": "inkOUT",
    "location_city": "Draper",
    "location_state": "UT",
    "method_used": "TEPR",
    "review_text": "***responding to their response…\nIt is simply not true that they have received no response from me. I text them on March 11th and after not hearing back, I sent a bubble “?”  To my text about scarring. After several days I received a text that I will have to come in and asked what time works best, which was just a few days ago. So the fact that they are saying they have made several attempts and haven't received a response is just simply not true.\nAlso them saying the pictures I attached are the ones showing irritations is also false. I didn’t even post those pictures original, I now have irritated photos posted. The pictures I posted are 2 months past my last appt. I have taken extremely good care of the wound (cause that is what it is) and the pictures are after all that extra care. That is the pictures of it healed! Which is why I text them about the scarring. You shouldn’t have to use tegaderm to not have scarring. This “tattoo removal” will scar you!\n\nDO NOT get tattoo removal here! You will be left with a permanent scar where your tattoo was.\n\nIt’s appalling that this company is still operating. Their practices are not just unethical, but downright harmful. They are knowingly scarring their clients and should be shut down immediately! Avoid this company at all costs!\n\nAnd for those that are thinking that I am just an angry customer and that there are enough good reviews to give it a try…I would encourage you to notice that none of the “good” reviews have before and after pictures. How would anyone give a good review for being permanently scarred??\n\nThese pics show the different stages. I have had 3 treatments and will never go back. This is the scar I am left with. 😖😔😡",
    "star_rating": 1,
    "review_date": "Edited a year ago",
    "review_date_iso": "2025-04-02T13:40:21Z",
    "review_date_edited_iso": "2025-04-07T04:47:12Z",
    "reviewer_name": "Britney De Jong",
    "reviewer_local_guide": true,
    "verified_source": "Google",
    "_place_title": "Rejuvatek Aesthetics providing inkOUT®",
    "_place_id": "ChIJwZ1KoJ6HUocRpaZ0Pq0XQaU",
    "_scrape_mode": "full",
    "_scrape_date": "2026-04-24",
    "source_url": "https://www.google.com/maps/reviews/data=!4m8!14m7!1m6!2m5!1sChZDSUhNMG9nS0VJQ0FnTUNJZ2UtSU9REAE!2m1!1s0x0:0xa54117ad3e74a6a5!3m1!1s2@1:CIHM0ogKEICAgMCIge-IOQ%7C%7C?hl=en",
    "pain_level": "unknown",
    "scarring_mentioned": "Yes",
    "sessions_completed": 3,
    "skin_type": "unknown",
    "use_case": "Complete",
    "result_rating": "Negative",
    "review_date_estimated": "2025-04-02",
    "review_date_label": "Apr 02, 2025 (verified from SerpAPI iso_date, last edited Apr 07, 2025)",
    "review_date_source": "verified_serpapi",
    "has_text": true,
    "text_note": null,
    "brand_name": "inkOUT",
    "multi_location_brand": true,
    "location_transition": false,
    "transition_note": null
  },
  {
    "provider_name": "inkOUT",
    "location_city": "Draper",
    "location_state": "UT",
    "method_used": "TEPR",
    "review_text": "Did two treatments - with little changes after each session. Was charged $1000 for two sessions. It is $500 per session. It would probably take 10+ sessions to remove at this rate. Laser is cheaper and much faster than the 3-hour painful appointments.\n\nI was also ghosted with no response during what was supposed to be my follow-up for 1 whole month before I was told my person had left the company. Just not a good experience, unfortunately all around. 10+ hours wasted. Lots of pain and 1k out of money with the entire tattoo still there... :(",
    "star_rating": 1,
    "review_date": "a year ago",
    "review_date_iso": "2025-01-23T15:56:06Z",
    "review_date_edited_iso": "2025-01-23T15:56:06Z",
    "reviewer_name": "B",
    "reviewer_local_guide": true,
    "verified_source": "Google",
    "_place_title": "Rejuvatek Aesthetics providing inkOUT®",
    "_place_id": "ChIJwZ1KoJ6HUocRpaZ0Pq0XQaU",
    "_scrape_mode": "full",
    "_scrape_date": "2026-04-24",
    "source_url": "https://www.google.com/maps/reviews/data=!4m8!14m7!1m6!2m5!1sChdDSUhNMG9nS0VJQ0FnSURfdXVXbWlBRRAB!2m1!1s0x0:0xa54117ad3e74a6a5!3m1!1s2@1:CIHM0ogKEICAgID_uuWmiAE%7C%7C?hl=en",
    "pain_level": 4,
    "scarring_mentioned": "No",
    "sessions_completed": 2,
    "skin_type": "unknown",
    "use_case": "Complete",
    "result_rating": "Negative",
    "review_date_estimated": "2025-01-23",
    "review_date_label": "Jan 23, 2025 (verified from SerpAPI iso_date, last edited Jan 23, 2025)",
    "review_date_source": "verified_serpapi",
    "has_text": true,
    "text_note": null,
    "brand_name": "inkOUT",
    "multi_location_brand": true,
    "location_transition": false,
    "transition_note": null
  },
  {
    "provider_name": "inkOUT",
    "location_city": "Draper",
    "location_state": "UT",
    "method_used": "TEPR",
    "review_text": "My experience at Tatt2away here in Draper has been wonderful! I was nervous at first but, with the help of Mandy Morrell, the process of getting my tattoo removed has been stress free and very exciting! I am very happy with the outcome so far and was super excited to see the ink be removed from my skin in one of the scabs that fell off! It’s so cool to see the healing and the progress. I’m grateful I found tatt2away and for the kindness and help that Mandy has shown me. Thank you!",
    "star_rating": 5,
    "review_date": "a year ago",
    "review_date_iso": "2024-12-12T21:06:44Z",
    "review_date_edited_iso": "2024-12-12T21:06:44Z",
    "reviewer_name": "Rachel Tew",
    "reviewer_local_guide": true,
    "verified_source": "Google",
    "_place_title": "Rejuvatek Aesthetics providing inkOUT®",
    "_place_id": "ChIJwZ1KoJ6HUocRpaZ0Pq0XQaU",
    "_scrape_mode": "full",
    "_scrape_date": "2026-04-24",
    "source_url": "https://www.google.com/maps/reviews/data=!4m8!14m7!1m6!2m5!1sChdDSUhNMG9nS0VJQ0FnSUN2LWZ1SGlnRRAB!2m1!1s0x0:0xa54117ad3e74a6a5!3m1!1s2@1:CIHM0ogKEICAgICv-fuHigE%7C%7C?hl=en",
    "pain_level": "unknown",
    "scarring_mentioned": "No",
    "sessions_completed": "unknown",
    "skin_type": "unknown",
    "use_case": "Complete",
    "result_rating": "Positive",
    "review_date_estimated": "2024-12-12",
    "review_date_label": "Dec 12, 2024 (verified from SerpAPI iso_date, last edited Dec 12, 2024)",
    "review_date_source": "verified_serpapi",
    "has_text": true,
    "text_note": null,
    "brand_name": "inkOUT",
    "multi_location_brand": true,
    "location_transition": false,
    "transition_note": null
  },
  {
    "provider_name": "inkOUT",
    "location_city": "Draper",
    "location_state": "UT",
    "method_used": "TEPR",
    "review_text": "This is an excellent way to get a better tattoo removal than laser. It’s fairly quick and easy and jazz is super professional and skilled. Obviously tattoo removal doesn’t feel amazing no matter what but I still have a good time chatting with jazz and fully trust her work.",
    "star_rating": 5,
    "review_date": "a year ago",
    "review_date_iso": "2024-11-26T22:30:39Z",
    "review_date_edited_iso": "2024-11-26T22:30:39Z",
    "reviewer_name": "Natalie Mullen",
    "reviewer_local_guide": true,
    "verified_source": "Google",
    "_place_title": "Rejuvatek Aesthetics providing inkOUT®",
    "_place_id": "ChIJwZ1KoJ6HUocRpaZ0Pq0XQaU",
    "_scrape_mode": "full",
    "_scrape_date": "2026-04-24",
    "source_url": "https://www.google.com/maps/reviews/data=!4m8!14m7!1m6!2m5!1sChdDSUhNMG9nS0VJQ0FnSUNQemNHMG1BRRAB!2m1!1s0x0:0xa54117ad3e74a6a5!3m1!1s2@1:CIHM0ogKEICAgICPzcG0mAE%7C%7C?hl=en",
    "pain_level": 3,
    "scarring_mentioned": "No",
    "sessions_completed": "unknown",
    "skin_type": "unknown",
    "use_case": "unknown",
    "result_rating": "Positive",
    "review_date_estimated": "2024-11-26",
    "review_date_label": "Nov 26, 2024 (verified from SerpAPI iso_date, last edited Nov 26, 2024)",
    "review_date_source": "verified_serpapi",
    "has_text": true,
    "text_note": null,
    "brand_name": "inkOUT",
    "multi_location_brand": true,
    "location_transition": false,
    "transition_note": null
  },
  {
    "provider_name": "inkOUT",
    "location_city": "Draper",
    "location_state": "UT",
    "method_used": "TEPR",
    "review_text": "Absolute worst place. My first appointment, Jazz forgot to give me her number after telling me to send her pictures of how my tattoo removal was healing in the next few days. I was calling the office with questions and trying to get her number, and no one answered. It wasn’t until she contacted me over a month later, saying she needed to do our next visit over the phone because she wasn’t going to be in the office, that i finally got her number. Setting up appointments afterwards was horrible, and took forever to actually get a response no matter how many times I called and texted. The whole process was taking so much longer than necessary. Eventually she got some help, but by then I had decided I was done with her forgetfulness and unprofessionalism. It’s not worth it. Get laser or a tattoo cover up honestly. By far the worst experience. No questions were answered, always rushed, and it was a WASTE.",
    "star_rating": 1,
    "review_date": "a year ago",
    "review_date_iso": "2024-11-16T02:18:13Z",
    "review_date_edited_iso": "2024-11-16T02:18:13Z",
    "reviewer_name": "jess",
    "reviewer_local_guide": true,
    "verified_source": "Google",
    "_place_title": "Rejuvatek Aesthetics providing inkOUT®",
    "_place_id": "ChIJwZ1KoJ6HUocRpaZ0Pq0XQaU",
    "_scrape_mode": "full",
    "_scrape_date": "2026-04-24",
    "source_url": "https://www.google.com/maps/reviews/data=!4m8!14m7!1m6!2m5!1sChZDSUhNMG9nS0VJQ0FnSUQzc1pMcWF3EAE!2m1!1s0x0:0xa54117ad3e74a6a5!3m1!1s2@1:CIHM0ogKEICAgID3sZLqaw%7C%7C?hl=en",
    "pain_level": "unknown",
    "scarring_mentioned": "No",
    "sessions_completed": "unknown",
    "skin_type": "unknown",
    "use_case": "unknown",
    "result_rating": "Negative",
    "review_date_estimated": "2024-11-16",
    "review_date_label": "Nov 16, 2024 (verified from SerpAPI iso_date, last edited Nov 16, 2024)",
    "review_date_source": "verified_serpapi",
    "has_text": true,
    "text_note": null,
    "brand_name": "inkOUT",
    "multi_location_brand": true,
    "location_transition": false,
    "transition_note": null
  },
  {
    "provider_name": "inkOUT",
    "location_city": "Draper",
    "location_state": "UT",
    "method_used": "TEPR",
    "review_text": "Mandy was awesome! She explained everything and was very nice in helping me feel comfortable. Tattoo removal was smooth and seamless.",
    "star_rating": 5,
    "review_date": "a year ago",
    "review_date_iso": "2024-10-17T22:04:46Z",
    "review_date_edited_iso": "2024-10-17T22:04:46Z",
    "reviewer_name": "Nicholas Demetropoulos",
    "reviewer_local_guide": true,
    "verified_source": "Google",
    "_place_title": "Rejuvatek Aesthetics providing inkOUT®",
    "_place_id": "ChIJwZ1KoJ6HUocRpaZ0Pq0XQaU",
    "_scrape_mode": "full",
    "_scrape_date": "2026-04-24",
    "source_url": "https://www.google.com/maps/reviews/data=!4m8!14m7!1m6!2m5!1sChZDSUhNMG9nS0VJQ0FnSUNYaWJEbmF3EAE!2m1!1s0x0:0xa54117ad3e74a6a5!3m1!1s2@1:CIHM0ogKEICAgICXibDnaw%7C%7C?hl=en",
    "pain_level": "unknown",
    "scarring_mentioned": "No",
    "sessions_completed": "unknown",
    "skin_type": "unknown",
    "use_case": "unknown",
    "result_rating": "Positive",
    "review_date_estimated": "2024-10-17",
    "review_date_label": "Oct 17, 2024 (verified from SerpAPI iso_date, last edited Oct 17, 2024)",
    "review_date_source": "verified_serpapi",
    "has_text": true,
    "text_note": null,
    "brand_name": "inkOUT",
    "multi_location_brand": true,
    "location_transition": false,
    "transition_note": null
  },
  {
    "provider_name": "inkOUT",
    "location_city": "Draper",
    "location_state": "UT",
    "method_used": "TEPR",
    "review_text": "I used this service to remove my eyebrow Microblading. I would not recommend it. I only went through with one of the two treatments, as the healing was so long, and I had vertical striped scabs that were very obvious. The striped scabs were to be expected, but the healing time was longer than expected. It also didn’t fully remove the ink in any of the strips that were treated. I also have slight scarring (pink, depressed skin). I started laser treatment today, and this seems like a much better and safer approach. I also contacted Tatt2away to ask for a partial refund since it didn’t remove my ink, and I wouldn’t be going through with the second prepaid treatment. I understand I signed a contract, but it would be good business practice and customer service to offer partial (half) refund.",
    "star_rating": 1,
    "review_date": "a year ago",
    "review_date_iso": "2024-09-23T19:04:22Z",
    "review_date_edited_iso": "2024-09-23T19:04:22Z",
    "reviewer_name": "Michelle Jaskierny",
    "reviewer_local_guide": true,
    "verified_source": "Google",
    "_place_title": "Rejuvatek Aesthetics providing inkOUT®",
    "_place_id": "ChIJwZ1KoJ6HUocRpaZ0Pq0XQaU",
    "_scrape_mode": "full",
    "_scrape_date": "2026-04-24",
    "source_url": "https://www.google.com/maps/reviews/data=!4m8!14m7!1m6!2m5!1sChdDSUhNMG9nS0VJQ0FnSUNubktPUzlBRRAB!2m1!1s0x0:0xa54117ad3e74a6a5!3m1!1s2@1:CIHM0ogKEICAgICnnKOS9AE%7C%7C?hl=en",
    "pain_level": "unknown",
    "scarring_mentioned": "Yes",
    "sessions_completed": 1,
    "skin_type": "unknown",
    "use_case": "Microblading",
    "result_rating": "Negative",
    "review_date_estimated": "2024-09-23",
    "review_date_label": "Sep 23, 2024 (verified from SerpAPI iso_date, last edited Sep 23, 2024)",
    "review_date_source": "verified_serpapi",
    "has_text": true,
    "text_note": null,
    "brand_name": "inkOUT",
    "multi_location_brand": true,
    "location_transition": false,
    "transition_note": null
  },
  {
    "provider_name": "inkOUT",
    "location_city": "Draper",
    "location_state": "UT",
    "method_used": "TEPR",
    "review_text": "I started my journey with Tatt2Away just two days ago and from the consultation to now I am completely impressed with the professionalism of Mandy Morrell who was my aesthetician. She is incredibly educated and was very kind to me. The office is EXTREMELY clean which is always a plus. I’m looking forward to our next session and for someone who doesn’t like lasers this was the place for me and I highly recommend it if you are looking to remove tattoos. The process is really exciting and physically I even feel better since my first session. Again, this is a great place to go if you are really serious about removing tattoos and Mandy Morrell is Amazing! Thank you Tatt2Away 💕",
    "star_rating": 5,
    "review_date": "a year ago",
    "review_date_iso": "2024-08-31T17:16:45Z",
    "review_date_edited_iso": "2024-08-31T17:16:45Z",
    "reviewer_name": "Noelle Staudt",
    "reviewer_local_guide": true,
    "verified_source": "Google",
    "_place_title": "Rejuvatek Aesthetics providing inkOUT®",
    "_place_id": "ChIJwZ1KoJ6HUocRpaZ0Pq0XQaU",
    "_scrape_mode": "full",
    "_scrape_date": "2026-04-24",
    "source_url": "https://www.google.com/maps/reviews/data=!4m8!14m7!1m6!2m5!1sChZDSUhNMG9nS0VJQ0FnSUNINkphdkNnEAE!2m1!1s0x0:0xa54117ad3e74a6a5!3m1!1s2@1:CIHM0ogKEICAgICH6JavCg%7C%7C?hl=en",
    "pain_level": "unknown",
    "scarring_mentioned": "No",
    "sessions_completed": 1,
    "skin_type": "unknown",
    "use_case": "Complete",
    "result_rating": "Positive",
    "review_date_estimated": "2024-08-31",
    "review_date_label": "Aug 31, 2024 (verified from SerpAPI iso_date, last edited Aug 31, 2024)",
    "review_date_source": "verified_serpapi",
    "has_text": true,
    "text_note": null,
    "brand_name": "inkOUT",
    "multi_location_brand": true,
    "location_transition": false,
    "transition_note": null
  },
  {
    "provider_name": "inkOUT",
    "location_city": "Draper",
    "location_state": "UT",
    "method_used": "TEPR",
    "review_text": "Very personable, clean and helpful",
    "star_rating": 5,
    "review_date": "a year ago",
    "review_date_iso": "2024-08-07T17:18:02Z",
    "review_date_edited_iso": "2024-08-07T17:18:02Z",
    "reviewer_name": "Tyson Olsen",
    "reviewer_local_guide": true,
    "verified_source": "Google",
    "_place_title": "Rejuvatek Aesthetics providing inkOUT®",
    "_place_id": "ChIJwZ1KoJ6HUocRpaZ0Pq0XQaU",
    "_scrape_mode": "full",
    "_scrape_date": "2026-04-24",
    "source_url": "https://www.google.com/maps/reviews/data=!4m8!14m7!1m6!2m5!1sChdDSUhNMG9nS0VJQ0FnSURibGN6dXNnRRAB!2m1!1s0x0:0xa54117ad3e74a6a5!3m1!1s2@1:CIHM0ogKEICAgIDblczusgE%7C%7C?hl=en",
    "pain_level": "unknown",
    "scarring_mentioned": "No",
    "sessions_completed": "unknown",
    "skin_type": "unknown",
    "use_case": "unknown",
    "result_rating": "Neutral",
    "review_date_estimated": "2024-08-07",
    "review_date_label": "Aug 07, 2024 (verified from SerpAPI iso_date, last edited Aug 07, 2024)",
    "review_date_source": "verified_serpapi",
    "has_text": true,
    "text_note": null,
    "brand_name": "inkOUT",
    "multi_location_brand": true,
    "location_transition": false,
    "transition_note": null
  },
  {
    "provider_name": "inkOUT",
    "location_city": "Draper",
    "location_state": "UT",
    "method_used": "TEPR",
    "review_text": "Jazz is extremely knowledgeable and explains the procedure in a way that is easy to understand.",
    "star_rating": 5,
    "review_date": "a year ago",
    "review_date_iso": "2024-06-24T20:07:32Z",
    "review_date_edited_iso": "2024-06-24T20:07:32Z",
    "reviewer_name": "ilene mcclellan",
    "reviewer_local_guide": true,
    "verified_source": "Google",
    "_place_title": "Rejuvatek Aesthetics providing inkOUT®",
    "_place_id": "ChIJwZ1KoJ6HUocRpaZ0Pq0XQaU",
    "_scrape_mode": "full",
    "_scrape_date": "2026-04-24",
    "source_url": "https://www.google.com/maps/reviews/data=!4m8!14m7!1m6!2m5!1sChZDSUhNMG9nS0VJQ0FnSURMc09UN01BEAE!2m1!1s0x0:0xa54117ad3e74a6a5!3m1!1s2@1:CIHM0ogKEICAgIDLsOT7MA%7C%7C?hl=en",
    "pain_level": "unknown",
    "scarring_mentioned": "No",
    "sessions_completed": "unknown",
    "skin_type": "unknown",
    "use_case": "unknown",
    "result_rating": "Neutral",
    "review_date_estimated": "2024-06-24",
    "review_date_label": "Jun 24, 2024 (verified from SerpAPI iso_date, last edited Jun 24, 2024)",
    "review_date_source": "verified_serpapi",
    "has_text": true,
    "text_note": null,
    "brand_name": "inkOUT",
    "multi_location_brand": true,
    "location_transition": false,
    "transition_note": null
  },
  {
    "provider_name": "inkOUT",
    "location_city": "Draper",
    "location_state": "UT",
    "method_used": "TEPR",
    "review_text": "This tattoo removal process is really interesting.  Tons of tiny little holes that heal the tattoo ink off your body.  I found the procedure to be pretty painless, definitely less than getting the tattoo.  The after care is long and tedious, but what do you expect from a removal?  I stuck to the letter on the aftercare and have clean, new, unscarred skin.  It works!  Also, better than burning yourself with a laser!  Jazz is fun and the shop is clean.  I recommend.",
    "star_rating": 5,
    "review_date": "a year ago",
    "review_date_iso": "2024-06-19T20:26:18Z",
    "review_date_edited_iso": "2024-06-19T20:27:45Z",
    "reviewer_name": "Ann von Brincken",
    "reviewer_local_guide": true,
    "verified_source": "Google",
    "_place_title": "Rejuvatek Aesthetics providing inkOUT®",
    "_place_id": "ChIJwZ1KoJ6HUocRpaZ0Pq0XQaU",
    "_scrape_mode": "full",
    "_scrape_date": "2026-04-24",
    "source_url": "https://www.google.com/maps/reviews/data=!4m8!14m7!1m6!2m5!1sChZDSUhNMG9nS0VJQ0FnSUNMZ1pQY1B3EAE!2m1!1s0x0:0xa54117ad3e74a6a5!3m1!1s2@1:CIHM0ogKEICAgICLgZPcPw%7C%7C?hl=en",
    "pain_level": 2,
    "scarring_mentioned": "Positive",
    "sessions_completed": "unknown",
    "skin_type": "unknown",
    "use_case": "Complete",
    "result_rating": "Positive",
    "review_date_estimated": "2024-06-19",
    "review_date_label": "Jun 19, 2024 (verified from SerpAPI iso_date, last edited Jun 19, 2024)",
    "review_date_source": "verified_serpapi",
    "has_text": true,
    "text_note": null,
    "brand_name": "inkOUT",
    "multi_location_brand": true,
    "location_transition": false,
    "transition_note": null
  },
  {
    "provider_name": "inkOUT",
    "location_city": "Draper",
    "location_state": "UT",
    "method_used": "TEPR",
    "review_text": "",
    "star_rating": 1,
    "review_date": "a year ago",
    "review_date_iso": "2024-05-02T20:54:11Z",
    "review_date_edited_iso": "2024-05-02T20:54:11Z",
    "reviewer_name": "khaled",
    "reviewer_local_guide": true,
    "verified_source": "Google",
    "_place_title": "Rejuvatek Aesthetics providing inkOUT®",
    "_place_id": "ChIJwZ1KoJ6HUocRpaZ0Pq0XQaU",
    "_scrape_mode": "full",
    "_scrape_date": "2026-04-24",
    "source_url": "https://www.google.com/maps/reviews/data=!4m8!14m7!1m6!2m5!1sChdDSUhNMG9nS0VJQ0FnSURqMXBUVF93RRAB!2m1!1s0x0:0xa54117ad3e74a6a5!3m1!1s2@1:CIHM0ogKEICAgIDj1pTT_wE%7C%7C?hl=en",
    "pain_level": "unknown",
    "scarring_mentioned": "No",
    "sessions_completed": "unknown",
    "skin_type": "unknown",
    "use_case": "unknown",
    "result_rating": "Negative",
    "review_date_estimated": "2024-05-02",
    "review_date_label": "May 02, 2024 (verified from SerpAPI iso_date, last edited May 02, 2024)",
    "review_date_source": "verified_serpapi",
    "has_text": false,
    "text_note": "Rating only — no written review text. Excluded from text-based analysis.",
    "brand_name": "inkOUT",
    "multi_location_brand": true,
    "location_transition": false,
    "transition_note": null
  },
  {
    "provider_name": "inkOUT",
    "location_city": "Draper",
    "location_state": "UT",
    "method_used": "TEPR",
    "review_text": "Tatt2away completely mutilated by 18 year olds arm. She went back to the clinic and they said she was having a “reaction”. After several visits with the dermatologist the doctor confirmed that it wasn’t a reaction, it was a completely botched tattoo removal that has left her with extreme keloid scars on her whole arm. The staff did not try to help her or offer her a refund or anything! Just a completely unconcerned well, your body is reacting. What an inhumane response to hurting such a young one so badly. She is undergoing medical treatment from the damage they caused but she will ultimately be scarred for life. For anyone considering this clinic I would stay well away. The damage they caused is severe and their unconcerned attitude regarding how badly they hurt her and botched the job shows TERRIBLE ethics. This photo is months post treatment. She will have these hard raised scars for life. It also seems like the business is flagging and removing negative reviews as this review is no longer publicly available. Wow.",
    "star_rating": 1,
    "review_date": "a year ago",
    "review_date_iso": "2024-05-01T22:56:11Z",
    "review_date_edited_iso": "2024-05-02T20:42:26Z",
    "reviewer_name": "Paula Cracknell",
    "reviewer_local_guide": true,
    "verified_source": "Google",
    "_place_title": "Rejuvatek Aesthetics providing inkOUT®",
    "_place_id": "ChIJwZ1KoJ6HUocRpaZ0Pq0XQaU",
    "_scrape_mode": "full",
    "_scrape_date": "2026-04-24",
    "source_url": "https://www.google.com/maps/reviews/data=!4m8!14m7!1m6!2m5!1sChZDSUhNMG9nS0VJQ0FnSURqNnYtNmVBEAE!2m1!1s0x0:0xa54117ad3e74a6a5!3m1!1s2@1:CIHM0ogKEICAgIDj6v-6eA%7C%7C?hl=en",
    "pain_level": "unknown",
    "scarring_mentioned": "Yes",
    "sessions_completed": "unknown",
    "skin_type": "unknown",
    "use_case": "unknown",
    "result_rating": "Negative",
    "review_date_estimated": "2024-05-01",
    "review_date_label": "May 01, 2024 (verified from SerpAPI iso_date, last edited May 02, 2024)",
    "review_date_source": "verified_serpapi",
    "has_text": true,
    "text_note": null,
    "brand_name": "inkOUT",
    "multi_location_brand": true,
    "location_transition": false,
    "transition_note": null
  },
  {
    "provider_name": "inkOUT",
    "location_city": "Draper",
    "location_state": "UT",
    "method_used": "TEPR",
    "review_text": "Jazz is amazing, so professional, honest and just great to work with.",
    "star_rating": 5,
    "review_date": "2 years ago",
    "review_date_iso": "2023-11-06T18:55:17Z",
    "review_date_edited_iso": "2023-11-06T18:55:17Z",
    "reviewer_name": "Jennifer Morris",
    "reviewer_local_guide": true,
    "verified_source": "Google",
    "_place_title": "Rejuvatek Aesthetics providing inkOUT®",
    "_place_id": "ChIJwZ1KoJ6HUocRpaZ0Pq0XQaU",
    "_scrape_mode": "full",
    "_scrape_date": "2026-04-24",
    "source_url": "https://www.google.com/maps/reviews/data=!4m8!14m7!1m6!2m5!1sChdDSUhNMG9nS0VJQ0FnSURGcHRqUDdnRRAB!2m1!1s0x0:0xa54117ad3e74a6a5!3m1!1s2@1:CIHM0ogKEICAgIDFptjP7gE%7C%7C?hl=en",
    "pain_level": "unknown",
    "scarring_mentioned": "No",
    "sessions_completed": "unknown",
    "skin_type": "unknown",
    "use_case": "unknown",
    "result_rating": "Neutral",
    "review_date_estimated": "2023-11-06",
    "review_date_label": "Nov 06, 2023 (verified from SerpAPI iso_date, last edited Nov 06, 2023)",
    "review_date_source": "verified_serpapi",
    "has_text": true,
    "text_note": null,
    "brand_name": "inkOUT",
    "multi_location_brand": true,
    "location_transition": false,
    "transition_note": null
  },
  {
    "provider_name": "inkOUT",
    "location_city": "Draper",
    "location_state": "UT",
    "method_used": "TEPR",
    "review_text": "This process is amazing and I love how safe it is! I’m so glad Tatt2Away provides a safe and non toxic way of removing unwanted tattoos! Jazz was incredible and so knowledgeable! I can’t recommend Tatt2Away enough!",
    "star_rating": 5,
    "review_date": "2 years ago",
    "review_date_iso": "2023-10-26T17:05:43Z",
    "review_date_edited_iso": "2023-10-26T17:05:43Z",
    "reviewer_name": "Morgan Mahler",
    "reviewer_local_guide": true,
    "verified_source": "Google",
    "_place_title": "Rejuvatek Aesthetics providing inkOUT®",
    "_place_id": "ChIJwZ1KoJ6HUocRpaZ0Pq0XQaU",
    "_scrape_mode": "full",
    "_scrape_date": "2026-04-24",
    "source_url": "https://www.google.com/maps/reviews/data=!4m8!14m7!1m6!2m5!1sChdDSUhNMG9nS0VJQ0FnSUQ1NlllU2dnRRAB!2m1!1s0x0:0xa54117ad3e74a6a5!3m1!1s2@1:CIHM0ogKEICAgID56YeSggE%7C%7C?hl=en",
    "pain_level": "unknown",
    "scarring_mentioned": "No",
    "sessions_completed": "unknown",
    "skin_type": "unknown",
    "use_case": "Complete",
    "result_rating": "Positive",
    "review_date_estimated": "2023-10-26",
    "review_date_label": "Oct 26, 2023 (verified from SerpAPI iso_date, last edited Oct 26, 2023)",
    "review_date_source": "verified_serpapi",
    "has_text": true,
    "text_note": null,
    "brand_name": "inkOUT",
    "multi_location_brand": true,
    "location_transition": false,
    "transition_note": null
  },
  {
    "provider_name": "inkOUT",
    "location_city": "Draper",
    "location_state": "UT",
    "method_used": "TEPR",
    "review_text": "Jazz is incredible! Gave me so much helpful advice and the removal itself was practically painless.",
    "star_rating": 5,
    "review_date": "2 years ago",
    "review_date_iso": "2023-09-06T17:28:55Z",
    "review_date_edited_iso": "2023-09-06T17:28:55Z",
    "reviewer_name": "Anna Nielsen",
    "reviewer_local_guide": true,
    "verified_source": "Google",
    "_place_title": "Rejuvatek Aesthetics providing inkOUT®",
    "_place_id": "ChIJwZ1KoJ6HUocRpaZ0Pq0XQaU",
    "_scrape_mode": "full",
    "_scrape_date": "2026-04-24",
    "source_url": "https://www.google.com/maps/reviews/data=!4m8!14m7!1m6!2m5!1sChZDSUhNMG9nS0VJQ0FnSUNaZ3NUaUlnEAE!2m1!1s0x0:0xa54117ad3e74a6a5!3m1!1s2@1:CIHM0ogKEICAgICZgsTiIg%7C%7C?hl=en",
    "pain_level": 1,
    "scarring_mentioned": "No",
    "sessions_completed": "unknown",
    "skin_type": "unknown",
    "use_case": "unknown",
    "result_rating": "Positive",
    "review_date_estimated": "2023-09-06",
    "review_date_label": "Sep 06, 2023 (verified from SerpAPI iso_date, last edited Sep 06, 2023)",
    "review_date_source": "verified_serpapi",
    "has_text": true,
    "text_note": null,
    "brand_name": "inkOUT",
    "multi_location_brand": true,
    "location_transition": false,
    "transition_note": null
  },
  {
    "provider_name": "inkOUT",
    "location_city": "Draper",
    "location_state": "UT",
    "method_used": "TEPR",
    "review_text": "Jazz is amazing at what she does and made me feel completely comfortable while she was working on me, highly recommend her to anyone looking for tattoo removal!",
    "star_rating": 5,
    "review_date": "2 years ago",
    "review_date_iso": "2023-05-10T00:29:10Z",
    "review_date_edited_iso": "2023-05-10T00:29:10Z",
    "reviewer_name": "Edith Fadhil",
    "reviewer_local_guide": true,
    "verified_source": "Google",
    "_place_title": "Rejuvatek Aesthetics providing inkOUT®",
    "_place_id": "ChIJwZ1KoJ6HUocRpaZ0Pq0XQaU",
    "_scrape_mode": "full",
    "_scrape_date": "2026-04-24",
    "source_url": "https://www.google.com/maps/reviews/data=!4m8!14m7!1m6!2m5!1sChZDSUhNMG9nS0VJQ0FnSUN4bU8tQlRBEAE!2m1!1s0x0:0xa54117ad3e74a6a5!3m1!1s2@1:CIHM0ogKEICAgICxmO-BTA%7C%7C?hl=en",
    "pain_level": "unknown",
    "scarring_mentioned": "No",
    "sessions_completed": "unknown",
    "skin_type": "unknown",
    "use_case": "Complete",
    "result_rating": "Positive",
    "review_date_estimated": "2023-05-10",
    "review_date_label": "May 10, 2023 (verified from SerpAPI iso_date, last edited May 10, 2023)",
    "review_date_source": "verified_serpapi",
    "has_text": true,
    "text_note": null,
    "brand_name": "inkOUT",
    "multi_location_brand": true,
    "location_transition": false,
    "transition_note": null
  },
  {
    "provider_name": "inkOUT",
    "location_city": "Draper",
    "location_state": "UT",
    "method_used": "TEPR",
    "review_text": "Not for melanin rich or scar prone skin. Left huge raised scars covering my arm.",
    "star_rating": 1,
    "review_date": "3 years ago",
    "review_date_iso": "2023-03-11T21:49:58Z",
    "review_date_edited_iso": "2023-03-11T21:50:14Z",
    "reviewer_name": "Shayla McGuire",
    "reviewer_local_guide": true,
    "verified_source": "Google",
    "_place_title": "Rejuvatek Aesthetics providing inkOUT®",
    "_place_id": "ChIJwZ1KoJ6HUocRpaZ0Pq0XQaU",
    "_scrape_mode": "full",
    "_scrape_date": "2026-04-24",
    "source_url": "https://www.google.com/maps/reviews/data=!4m8!14m7!1m6!2m5!1sChdDSUhNMG9nS0VJQ0FnSURoaWJfXzhnRRAB!2m1!1s0x0:0xa54117ad3e74a6a5!3m1!1s2@1:CIHM0ogKEICAgIDhib__8gE%7C%7C?hl=en",
    "pain_level": "unknown",
    "scarring_mentioned": "Yes",
    "sessions_completed": "unknown",
    "skin_type": "Dark",
    "use_case": "unknown",
    "result_rating": "Negative",
    "review_date_estimated": "2023-03-11",
    "review_date_label": "Mar 11, 2023 (verified from SerpAPI iso_date, last edited Mar 11, 2023)",
    "review_date_source": "verified_serpapi",
    "has_text": true,
    "text_note": null,
    "brand_name": "inkOUT",
    "multi_location_brand": true,
    "location_transition": false,
    "transition_note": null
  },
  {
    "provider_name": "inkOUT",
    "location_city": "Draper",
    "location_state": "UT",
    "method_used": "TEPR",
    "review_text": "Honestly such an amazing experience. Jazz helped so much and was very well informed on everything she was doing. I was nervous because the tattoo I have is older and my skin had scarred over. She reassured me about the pain and the procedure was less painful than when I got the tattoo. I look forward to finishing up this process with her.",
    "star_rating": 5,
    "review_date": "3 years ago",
    "review_date_iso": "2023-03-11T01:08:19Z",
    "review_date_edited_iso": "2023-03-11T01:08:19Z",
    "reviewer_name": "Alyx Kanosh",
    "reviewer_local_guide": true,
    "verified_source": "Google",
    "_place_title": "Rejuvatek Aesthetics providing inkOUT®",
    "_place_id": "ChIJwZ1KoJ6HUocRpaZ0Pq0XQaU",
    "_scrape_mode": "full",
    "_scrape_date": "2026-04-24",
    "source_url": "https://www.google.com/maps/reviews/data=!4m8!14m7!1m6!2m5!1sChdDSUhNMG9nS0VJQ0FnSURoa2JMejdRRRAB!2m1!1s0x0:0xa54117ad3e74a6a5!3m1!1s2@1:CIHM0ogKEICAgIDhkbLz7QE%7C%7C?hl=en",
    "pain_level": 2,
    "scarring_mentioned": "No",
    "sessions_completed": "unknown",
    "skin_type": "unknown",
    "use_case": "Complete",
    "result_rating": "Positive",
    "review_date_estimated": "2023-03-11",
    "review_date_label": "Mar 11, 2023 (verified from SerpAPI iso_date, last edited Mar 11, 2023)",
    "review_date_source": "verified_serpapi",
    "has_text": true,
    "text_note": null,
    "brand_name": "inkOUT",
    "multi_location_brand": true,
    "location_transition": false,
    "transition_note": null
  },
  {
    "provider_name": "inkOUT",
    "location_city": "Draper",
    "location_state": "UT",
    "method_used": "TEPR",
    "review_text": "Jazz is simply the best! Her studio space is very clean. She is extremely knowledgeable and will set you up on the perfect path for your tattoo removal. I am SO happy I found her before going through any more laser treatments.",
    "star_rating": 5,
    "review_date": "3 years ago",
    "review_date_iso": "2023-03-02T20:10:01Z",
    "review_date_edited_iso": "2023-03-02T20:10:01Z",
    "reviewer_name": "Morganne Jones",
    "reviewer_local_guide": true,
    "verified_source": "Google",
    "_place_title": "Rejuvatek Aesthetics providing inkOUT®",
    "_place_id": "ChIJwZ1KoJ6HUocRpaZ0Pq0XQaU",
    "_scrape_mode": "full",
    "_scrape_date": "2026-04-24",
    "source_url": "https://www.google.com/maps/reviews/data=!4m8!14m7!1m6!2m5!1sChdDSUhNMG9nS0VJQ0FnSURoOUxYTXlBRRAB!2m1!1s0x0:0xa54117ad3e74a6a5!3m1!1s2@1:CIHM0ogKEICAgIDh9LXMyAE%7C%7C?hl=en",
    "pain_level": "unknown",
    "scarring_mentioned": "No",
    "sessions_completed": "unknown",
    "skin_type": "unknown",
    "use_case": "unknown",
    "result_rating": "Positive",
    "review_date_estimated": "2023-03-02",
    "review_date_label": "Mar 02, 2023 (verified from SerpAPI iso_date, last edited Mar 02, 2023)",
    "review_date_source": "verified_serpapi",
    "has_text": true,
    "text_note": null,
    "brand_name": "inkOUT",
    "multi_location_brand": true,
    "location_transition": false,
    "transition_note": null
  },
  {
    "provider_name": "inkOUT",
    "location_city": "Draper",
    "location_state": "UT",
    "method_used": "TEPR",
    "review_text": "I was very skeptical at trying this process at first, but that changed quickly after my first treatment. The process was and is very easy and Jazz is amazing and makes you feel right at home like you are part of the family. I can't wait for my next appointment and I'm excited to see the results.",
    "star_rating": 5,
    "review_date": "3 years ago",
    "review_date_iso": "2023-02-18T01:18:14Z",
    "review_date_edited_iso": "2023-02-18T01:18:14Z",
    "reviewer_name": "Cody Barton",
    "reviewer_local_guide": true,
    "verified_source": "Google",
    "_place_title": "Rejuvatek Aesthetics providing inkOUT®",
    "_place_id": "ChIJwZ1KoJ6HUocRpaZ0Pq0XQaU",
    "_scrape_mode": "full",
    "_scrape_date": "2026-04-24",
    "source_url": "https://www.google.com/maps/reviews/data=!4m8!14m7!1m6!2m5!1sChdDSUhNMG9nS0VJQ0FnSUNoNVlTa2tBRRAB!2m1!1s0x0:0xa54117ad3e74a6a5!3m1!1s2@1:CIHM0ogKEICAgICh5YSkkAE%7C%7C?hl=en",
    "pain_level": "unknown",
    "scarring_mentioned": "No",
    "sessions_completed": 1,
    "skin_type": "unknown",
    "use_case": "unknown",
    "result_rating": "Positive",
    "review_date_estimated": "2023-02-18",
    "review_date_label": "Feb 18, 2023 (verified from SerpAPI iso_date, last edited Feb 18, 2023)",
    "review_date_source": "verified_serpapi",
    "has_text": true,
    "text_note": null,
    "brand_name": "inkOUT",
    "multi_location_brand": true,
    "location_transition": false,
    "transition_note": null
  },
  {
    "provider_name": "inkOUT",
    "location_city": "Draper",
    "location_state": "UT",
    "method_used": "TEPR",
    "review_text": "I'm starting my process to remove a tattoo. The attention has been amazing, Jazz is incredibly kind and explains very well all the steps that I need to do to get a successful treatment. She is very professional and always willing to resolve all my doubts.\nThanks.",
    "star_rating": 5,
    "review_date": "3 years ago",
    "review_date_iso": "2023-01-05T03:02:27Z",
    "review_date_edited_iso": "2023-01-05T03:08:06Z",
    "reviewer_name": "Dora Betancur",
    "reviewer_local_guide": true,
    "verified_source": "Google",
    "_place_title": "Rejuvatek Aesthetics providing inkOUT®",
    "_place_id": "ChIJwZ1KoJ6HUocRpaZ0Pq0XQaU",
    "_scrape_mode": "full",
    "_scrape_date": "2026-04-24",
    "source_url": "https://www.google.com/maps/reviews/data=!4m8!14m7!1m6!2m5!1sChdDSUhNMG9nS0VJQ0FnSUNCbTU3RndnRRAB!2m1!1s0x0:0xa54117ad3e74a6a5!3m1!1s2@1:CIHM0ogKEICAgICBm57FwgE%7C%7C?hl=en",
    "pain_level": "unknown",
    "scarring_mentioned": "No",
    "sessions_completed": "unknown",
    "skin_type": "unknown",
    "use_case": "Complete",
    "result_rating": "Neutral",
    "review_date_estimated": "2023-01-05",
    "review_date_label": "Jan 05, 2023 (verified from SerpAPI iso_date, last edited Jan 05, 2023)",
    "review_date_source": "verified_serpapi",
    "has_text": true,
    "text_note": null,
    "brand_name": "inkOUT",
    "multi_location_brand": true,
    "location_transition": false,
    "transition_note": null
  },
  {
    "provider_name": "inkOUT",
    "location_city": "Draper",
    "location_state": "UT",
    "method_used": "TEPR",
    "review_text": "Jazz was sensational!  She is excellent at her craft, and it's comforting to know she has a nursing background. She numbed my arm very well so I didn't feel much pain at all!  Jazz also has cool taste I'm music, her office has a chill vibe and she was able to get the job done effectively while having lighthearted conversation the entire time.   Tattoo removals don't sound like a fun experience, but if Jazz is doing the job, I know I can look forward to my next treatment.   Jazz rocks!",
    "star_rating": 5,
    "review_date": "3 years ago",
    "review_date_iso": "2022-12-10T00:20:03Z",
    "review_date_edited_iso": "2022-12-10T00:20:03Z",
    "reviewer_name": "Ethan Schaecher",
    "reviewer_local_guide": true,
    "verified_source": "Google",
    "_place_title": "Rejuvatek Aesthetics providing inkOUT®",
    "_place_id": "ChIJwZ1KoJ6HUocRpaZ0Pq0XQaU",
    "_scrape_mode": "full",
    "_scrape_date": "2026-04-24",
    "source_url": "https://www.google.com/maps/reviews/data=!4m8!14m7!1m6!2m5!1sChZDSUhNMG9nS0VJQ0FnSUQtNjh5SlBnEAE!2m1!1s0x0:0xa54117ad3e74a6a5!3m1!1s2@1:CIHM0ogKEICAgID-68yJPg%7C%7C?hl=en",
    "pain_level": 2,
    "scarring_mentioned": "No",
    "sessions_completed": "unknown",
    "skin_type": "unknown",
    "use_case": "unknown",
    "result_rating": "Positive",
    "review_date_estimated": "2022-12-10",
    "review_date_label": "Dec 10, 2022 (verified from SerpAPI iso_date, last edited Dec 10, 2022)",
    "review_date_source": "verified_serpapi",
    "has_text": true,
    "text_note": null,
    "brand_name": "inkOUT",
    "multi_location_brand": true,
    "location_transition": false,
    "transition_note": null
  },
  {
    "provider_name": "inkOUT",
    "location_city": "Draper",
    "location_state": "UT",
    "method_used": "TEPR",
    "review_text": "Jazz is very professional and she makes sure you understand how everything works. My tattoo has left a lot of scar tissue and was also very deep. A lot of my tattoo has been removed and my scar tissue is also not as bad it was which is very surprising. It’s definitely flattened it out a lot. I’m very happy with the results I’m getting. So thank you jazz.",
    "star_rating": 5,
    "review_date": "3 years ago",
    "review_date_iso": "2022-11-22T19:59:44Z",
    "review_date_edited_iso": "2022-11-22T19:59:44Z",
    "reviewer_name": "Joshua Stratton",
    "reviewer_local_guide": true,
    "verified_source": "Google",
    "_place_title": "Rejuvatek Aesthetics providing inkOUT®",
    "_place_id": "ChIJwZ1KoJ6HUocRpaZ0Pq0XQaU",
    "_scrape_mode": "full",
    "_scrape_date": "2026-04-24",
    "source_url": "https://www.google.com/maps/reviews/data=!4m8!14m7!1m6!2m5!1sChZDSUhNMG9nS0VJQ0FnSUQtOU1fWGFREAE!2m1!1s0x0:0xa54117ad3e74a6a5!3m1!1s2@1:CIHM0ogKEICAgID-9M_XaQ%7C%7C?hl=en",
    "pain_level": "unknown",
    "scarring_mentioned": "No",
    "sessions_completed": "unknown",
    "skin_type": "unknown",
    "use_case": "Complete",
    "result_rating": "Positive",
    "review_date_estimated": "2022-11-22",
    "review_date_label": "Nov 22, 2022 (verified from SerpAPI iso_date, last edited Nov 22, 2022)",
    "review_date_source": "verified_serpapi",
    "has_text": true,
    "text_note": null,
    "brand_name": "inkOUT",
    "multi_location_brand": true,
    "location_transition": false,
    "transition_note": null
  },
  {
    "provider_name": "inkOUT",
    "location_city": "Draper",
    "location_state": "UT",
    "method_used": "TEPR",
    "review_text": "Jazz is very professional and educates you about every aspect of the process!",
    "star_rating": 5,
    "review_date": "3 years ago",
    "review_date_iso": "2022-11-17T18:50:29Z",
    "review_date_edited_iso": "2022-11-17T18:50:29Z",
    "reviewer_name": "Angie Quinlan",
    "reviewer_local_guide": true,
    "verified_source": "Google",
    "_place_title": "Rejuvatek Aesthetics providing inkOUT®",
    "_place_id": "ChIJwZ1KoJ6HUocRpaZ0Pq0XQaU",
    "_scrape_mode": "full",
    "_scrape_date": "2026-04-24",
    "source_url": "https://www.google.com/maps/reviews/data=!4m8!14m7!1m6!2m5!1sChdDSUhNMG9nS0VJQ0FnSUMtdi1PdjhnRRAB!2m1!1s0x0:0xa54117ad3e74a6a5!3m1!1s2@1:CIHM0ogKEICAgIC-v-Ov8gE%7C%7C?hl=en",
    "pain_level": "unknown",
    "scarring_mentioned": "No",
    "sessions_completed": "unknown",
    "skin_type": "unknown",
    "use_case": "unknown",
    "result_rating": "Neutral",
    "review_date_estimated": "2022-11-17",
    "review_date_label": "Nov 17, 2022 (verified from SerpAPI iso_date, last edited Nov 17, 2022)",
    "review_date_source": "verified_serpapi",
    "has_text": true,
    "text_note": null,
    "brand_name": "inkOUT",
    "multi_location_brand": true,
    "location_transition": false,
    "transition_note": null
  },
  {
    "provider_name": "inkOUT",
    "location_city": "Draper",
    "location_state": "UT",
    "method_used": "TEPR",
    "review_text": "",
    "star_rating": 5,
    "review_date": "3 years ago",
    "review_date_iso": "2022-11-10T00:38:32Z",
    "review_date_edited_iso": "2022-11-10T00:38:32Z",
    "reviewer_name": "José Carlos",
    "reviewer_local_guide": true,
    "verified_source": "Google",
    "_place_title": "Rejuvatek Aesthetics providing inkOUT®",
    "_place_id": "ChIJwZ1KoJ6HUocRpaZ0Pq0XQaU",
    "_scrape_mode": "full",
    "_scrape_date": "2026-04-24",
    "source_url": "https://www.google.com/maps/reviews/data=!4m8!14m7!1m6!2m5!1sChZDSUhNMG9nS0VJQ0FnSUMtOVptMUdREAE!2m1!1s0x0:0xa54117ad3e74a6a5!3m1!1s2@1:CIHM0ogKEICAgIC-9Zm1GQ%7C%7C?hl=en",
    "pain_level": "unknown",
    "scarring_mentioned": "No",
    "sessions_completed": "unknown",
    "skin_type": "unknown",
    "use_case": "unknown",
    "result_rating": "Positive",
    "review_date_estimated": "2022-11-10",
    "review_date_label": "Nov 10, 2022 (verified from SerpAPI iso_date, last edited Nov 10, 2022)",
    "review_date_source": "verified_serpapi",
    "has_text": false,
    "text_note": "Rating only — no written review text. Excluded from text-based analysis.",
    "brand_name": "inkOUT",
    "multi_location_brand": true,
    "location_transition": false,
    "transition_note": null
  },
  {
    "provider_name": "inkOUT",
    "location_city": "Draper",
    "location_state": "UT",
    "method_used": "TEPR",
    "review_text": "Jazz was knowledgeable and great. Couldn't ask for a better treatment.",
    "star_rating": 5,
    "review_date": "3 years ago",
    "review_date_iso": "2022-10-21T01:26:23Z",
    "review_date_edited_iso": "2022-10-21T01:26:23Z",
    "reviewer_name": "Eric Parry",
    "reviewer_local_guide": true,
    "verified_source": "Google",
    "_place_title": "Rejuvatek Aesthetics providing inkOUT®",
    "_place_id": "ChIJwZ1KoJ6HUocRpaZ0Pq0XQaU",
    "_scrape_mode": "full",
    "_scrape_date": "2026-04-24",
    "source_url": "https://www.google.com/maps/reviews/data=!4m8!14m7!1m6!2m5!1sChZDSUhNMG9nS0VJQ0FnSURleC16SUZREAE!2m1!1s0x0:0xa54117ad3e74a6a5!3m1!1s2@1:CIHM0ogKEICAgIDex-zIFQ%7C%7C?hl=en",
    "pain_level": "unknown",
    "scarring_mentioned": "No",
    "sessions_completed": "unknown",
    "skin_type": "unknown",
    "use_case": "unknown",
    "result_rating": "Positive",
    "review_date_estimated": "2022-10-21",
    "review_date_label": "Oct 21, 2022 (verified from SerpAPI iso_date, last edited Oct 21, 2022)",
    "review_date_source": "verified_serpapi",
    "has_text": true,
    "text_note": null,
    "brand_name": "inkOUT",
    "multi_location_brand": true,
    "location_transition": false,
    "transition_note": null
  },
  {
    "provider_name": "inkOUT",
    "location_city": "Draper",
    "location_state": "UT",
    "method_used": "TEPR",
    "review_text": "Jazz is great. She took the time to put me at ease and is very personable. I highly recommend her.",
    "star_rating": 5,
    "review_date": "3 years ago",
    "review_date_iso": "2022-10-07T17:30:08Z",
    "review_date_edited_iso": "2022-10-07T17:30:08Z",
    "reviewer_name": "Eric Holman",
    "reviewer_local_guide": true,
    "verified_source": "Google",
    "_place_title": "Rejuvatek Aesthetics providing inkOUT®",
    "_place_id": "ChIJwZ1KoJ6HUocRpaZ0Pq0XQaU",
    "_scrape_mode": "full",
    "_scrape_date": "2026-04-24",
    "source_url": "https://www.google.com/maps/reviews/data=!4m8!14m7!1m6!2m5!1sChZDSUhNMG9nS0VJQ0FnSURlNnRqTkhBEAE!2m1!1s0x0:0xa54117ad3e74a6a5!3m1!1s2@1:CIHM0ogKEICAgIDe6tjNHA%7C%7C?hl=en",
    "pain_level": "unknown",
    "scarring_mentioned": "No",
    "sessions_completed": "unknown",
    "skin_type": "unknown",
    "use_case": "unknown",
    "result_rating": "Neutral",
    "review_date_estimated": "2022-10-07",
    "review_date_label": "Oct 07, 2022 (verified from SerpAPI iso_date, last edited Oct 07, 2022)",
    "review_date_source": "verified_serpapi",
    "has_text": true,
    "text_note": null,
    "brand_name": "inkOUT",
    "multi_location_brand": true,
    "location_transition": false,
    "transition_note": null
  },
  {
    "provider_name": "inkOUT",
    "location_city": "Draper",
    "location_state": "UT",
    "method_used": "TEPR",
    "review_text": "On my 4th treatment.  The sessions are making my tattoo dissappear. I voukdnt be happier with how it's going. Jazz is my technician and she makes every meeting aersome. Definitely continuing till it's gone!",
    "star_rating": 5,
    "review_date": "3 years ago",
    "review_date_iso": "2022-09-30T20:56:39Z",
    "review_date_edited_iso": "2022-09-30T20:56:39Z",
    "reviewer_name": "Justin Mick",
    "reviewer_local_guide": true,
    "verified_source": "Google",
    "_place_title": "Rejuvatek Aesthetics providing inkOUT®",
    "_place_id": "ChIJwZ1KoJ6HUocRpaZ0Pq0XQaU",
    "_scrape_mode": "full",
    "_scrape_date": "2026-04-24",
    "source_url": "https://www.google.com/maps/reviews/data=!4m8!14m7!1m6!2m5!1sChZDSUhNMG9nS0VJQ0FnSURlcUpQc0NBEAE!2m1!1s0x0:0xa54117ad3e74a6a5!3m1!1s2@1:CIHM0ogKEICAgIDeqJPsCA%7C%7C?hl=en",
    "pain_level": "unknown",
    "scarring_mentioned": "No",
    "sessions_completed": 4,
    "skin_type": "unknown",
    "use_case": "Complete",
    "result_rating": "Positive",
    "review_date_estimated": "2022-09-30",
    "review_date_label": "Sep 30, 2022 (verified from SerpAPI iso_date, last edited Sep 30, 2022)",
    "review_date_source": "verified_serpapi",
    "has_text": true,
    "text_note": null,
    "brand_name": "inkOUT",
    "multi_location_brand": true,
    "location_transition": false,
    "transition_note": null
  },
  {
    "provider_name": "inkOUT",
    "location_city": "Draper",
    "location_state": "UT",
    "method_used": "TEPR",
    "review_text": "Had tattoo removal performed by Jazz. Worked out great  and is really helping to get my unwanted tattoo gone over time. Jazz is great and really helped me through the process and the aftercare. Gave great instructions and is very caring and concerned about my welfare. Would recommend to someone looking to remove an unwanted tattoo.",
    "star_rating": 5,
    "review_date": "3 years ago",
    "review_date_iso": "2022-09-27T15:32:01Z",
    "review_date_edited_iso": "2022-09-27T15:32:01Z",
    "reviewer_name": "Yvonne Smith",
    "reviewer_local_guide": true,
    "verified_source": "Google",
    "_place_title": "Rejuvatek Aesthetics providing inkOUT®",
    "_place_id": "ChIJwZ1KoJ6HUocRpaZ0Pq0XQaU",
    "_scrape_mode": "full",
    "_scrape_date": "2026-04-24",
    "source_url": "https://www.google.com/maps/reviews/data=!4m8!14m7!1m6!2m5!1sChdDSUhNMG9nS0VJQ0FnSUNlNzhuejZnRRAB!2m1!1s0x0:0xa54117ad3e74a6a5!3m1!1s2@1:CIHM0ogKEICAgICe78nz6gE%7C%7C?hl=en",
    "pain_level": "unknown",
    "scarring_mentioned": "No",
    "sessions_completed": "unknown",
    "skin_type": "unknown",
    "use_case": "Complete",
    "result_rating": "Positive",
    "review_date_estimated": "2022-09-27",
    "review_date_label": "Sep 27, 2022 (verified from SerpAPI iso_date, last edited Sep 27, 2022)",
    "review_date_source": "verified_serpapi",
    "has_text": true,
    "text_note": null,
    "brand_name": "inkOUT",
    "multi_location_brand": true,
    "location_transition": false,
    "transition_note": null
  },
  {
    "provider_name": "inkOUT",
    "location_city": "Draper",
    "location_state": "UT",
    "method_used": "TEPR",
    "review_text": "Awesome experience. Had my first treatment today and can't wait for my next! Jazz is very friendly and awesome. Definitely looking forward to my next session!",
    "star_rating": 5,
    "review_date": "4 years ago",
    "review_date_iso": "2022-04-07T17:47:55Z",
    "review_date_edited_iso": "2022-04-07T17:47:55Z",
    "reviewer_name": "justin mick",
    "reviewer_local_guide": true,
    "verified_source": "Google",
    "_place_title": "Rejuvatek Aesthetics providing inkOUT®",
    "_place_id": "ChIJwZ1KoJ6HUocRpaZ0Pq0XQaU",
    "_scrape_mode": "full",
    "_scrape_date": "2026-04-24",
    "source_url": "https://www.google.com/maps/reviews/data=!4m8!14m7!1m6!2m5!1sChZDSUhNMG9nS0VJQ0FnSURXejhPOUxnEAE!2m1!1s0x0:0xa54117ad3e74a6a5!3m1!1s2@1:CIHM0ogKEICAgIDWz8O9Lg%7C%7C?hl=en",
    "pain_level": "unknown",
    "scarring_mentioned": "No",
    "sessions_completed": 1,
    "skin_type": "unknown",
    "use_case": "unknown",
    "result_rating": "Positive",
    "review_date_estimated": "2022-04-07",
    "review_date_label": "Apr 07, 2022 (verified from SerpAPI iso_date, last edited Apr 07, 2022)",
    "review_date_source": "verified_serpapi",
    "has_text": true,
    "text_note": null,
    "brand_name": "inkOUT",
    "multi_location_brand": true,
    "location_transition": false,
    "transition_note": null
  },
  {
    "provider_name": "inkOUT",
    "location_city": "Draper",
    "location_state": "UT",
    "method_used": "TEPR",
    "review_text": "Jazz, was very professional and made sure that I understood all the information she had given me on the process of removal of the tattoo.\nThe procedure wasn’t painful just a bit uncomfortable and I highly recommend Jazz to do the removals.",
    "star_rating": 5,
    "review_date": "4 years ago",
    "review_date_iso": "2022-03-14T17:33:14Z",
    "review_date_edited_iso": "2022-03-14T17:33:14Z",
    "reviewer_name": "Lisa Todaro",
    "reviewer_local_guide": true,
    "verified_source": "Google",
    "_place_title": "Rejuvatek Aesthetics providing inkOUT®",
    "_place_id": "ChIJwZ1KoJ6HUocRpaZ0Pq0XQaU",
    "_scrape_mode": "full",
    "_scrape_date": "2026-04-24",
    "source_url": "https://www.google.com/maps/reviews/data=!4m8!14m7!1m6!2m5!1sChZDSUhNMG9nS0VJQ0FnSURXMklxVWJREAE!2m1!1s0x0:0xa54117ad3e74a6a5!3m1!1s2@1:CIHM0ogKEICAgIDW2IqUbQ%7C%7C?hl=en",
    "pain_level": 2,
    "scarring_mentioned": "No",
    "sessions_completed": "unknown",
    "skin_type": "unknown",
    "use_case": "Complete",
    "result_rating": "Positive",
    "review_date_estimated": "2022-03-14",
    "review_date_label": "Mar 14, 2022 (verified from SerpAPI iso_date, last edited Mar 14, 2022)",
    "review_date_source": "verified_serpapi",
    "has_text": true,
    "text_note": null,
    "brand_name": "inkOUT",
    "multi_location_brand": true,
    "location_transition": false,
    "transition_note": null
  },
  {
    "provider_name": "inkOUT",
    "location_city": "Draper",
    "location_state": "UT",
    "method_used": "TEPR",
    "review_text": "",
    "star_rating": 5,
    "review_date": "4 years ago",
    "review_date_iso": "2022-03-03T00:13:20Z",
    "review_date_edited_iso": "2022-03-03T00:13:20Z",
    "reviewer_name": "Dakotawest",
    "reviewer_local_guide": true,
    "verified_source": "Google",
    "_place_title": "Rejuvatek Aesthetics providing inkOUT®",
    "_place_id": "ChIJwZ1KoJ6HUocRpaZ0Pq0XQaU",
    "_scrape_mode": "full",
    "_scrape_date": "2026-04-24",
    "source_url": "https://www.google.com/maps/reviews/data=!4m8!14m7!1m6!2m5!1sChdDSUhNMG9nS0VJQ0FnSUNXcGVPZDZBRRAB!2m1!1s0x0:0xa54117ad3e74a6a5!3m1!1s2@1:CIHM0ogKEICAgICWpeOd6AE%7C%7C?hl=en",
    "pain_level": "unknown",
    "scarring_mentioned": "No",
    "sessions_completed": "unknown",
    "skin_type": "unknown",
    "use_case": "unknown",
    "result_rating": "Positive",
    "review_date_estimated": "2022-03-03",
    "review_date_label": "Mar 03, 2022 (verified from SerpAPI iso_date, last edited Mar 03, 2022)",
    "review_date_source": "verified_serpapi",
    "has_text": false,
    "text_note": "Rating only — no written review text. Excluded from text-based analysis.",
    "brand_name": "inkOUT",
    "multi_location_brand": true,
    "location_transition": false,
    "transition_note": null
  },
  {
    "provider_name": "inkOUT",
    "location_city": "Draper",
    "location_state": "UT",
    "method_used": "TEPR",
    "review_text": "I have had nothing but good experiences and things to say about jazz and this company. She has been so kind and helping me get rid of my tattoo! Highly recommended",
    "star_rating": 5,
    "review_date": "4 years ago",
    "review_date_iso": "2022-02-17T01:01:59Z",
    "review_date_edited_iso": "2022-02-17T01:01:59Z",
    "reviewer_name": "Emily Ford",
    "reviewer_local_guide": true,
    "verified_source": "Google",
    "_place_title": "Rejuvatek Aesthetics providing inkOUT®",
    "_place_id": "ChIJwZ1KoJ6HUocRpaZ0Pq0XQaU",
    "_scrape_mode": "full",
    "_scrape_date": "2026-04-24",
    "source_url": "https://www.google.com/maps/reviews/data=!4m8!14m7!1m6!2m5!1sChdDSUhNMG9nS0VJQ0FnSUNXbUtEZmlRRRAB!2m1!1s0x0:0xa54117ad3e74a6a5!3m1!1s2@1:CIHM0ogKEICAgICWmKDfiQE%7C%7C?hl=en",
    "pain_level": "unknown",
    "scarring_mentioned": "No",
    "sessions_completed": "unknown",
    "skin_type": "unknown",
    "use_case": "Complete",
    "result_rating": "Positive",
    "review_date_estimated": "2022-02-17",
    "review_date_label": "Feb 17, 2022 (verified from SerpAPI iso_date, last edited Feb 17, 2022)",
    "review_date_source": "verified_serpapi",
    "has_text": true,
    "text_note": null,
    "brand_name": "inkOUT",
    "multi_location_brand": true,
    "location_transition": false,
    "transition_note": null
  },
  {
    "provider_name": "inkOUT",
    "location_city": "Draper",
    "location_state": "UT",
    "method_used": "TEPR",
    "review_text": "Did an amazing job! Great bedside manners. Super friendly",
    "star_rating": 5,
    "review_date": "4 years ago",
    "review_date_iso": "2022-02-15T02:28:55Z",
    "review_date_edited_iso": "2022-02-15T02:28:55Z",
    "reviewer_name": "Jessica Taylor",
    "reviewer_local_guide": true,
    "verified_source": "Google",
    "_place_title": "Rejuvatek Aesthetics providing inkOUT®",
    "_place_id": "ChIJwZ1KoJ6HUocRpaZ0Pq0XQaU",
    "_scrape_mode": "full",
    "_scrape_date": "2026-04-24",
    "source_url": "https://www.google.com/maps/reviews/data=!4m8!14m7!1m6!2m5!1sChdDSUhNMG9nS0VJQ0FnSUNXb0lfYTJBRRAB!2m1!1s0x0:0xa54117ad3e74a6a5!3m1!1s2@1:CIHM0ogKEICAgICWoI_a2AE%7C%7C?hl=en",
    "pain_level": "unknown",
    "scarring_mentioned": "No",
    "sessions_completed": "unknown",
    "skin_type": "unknown",
    "use_case": "unknown",
    "result_rating": "Positive",
    "review_date_estimated": "2022-02-15",
    "review_date_label": "Feb 15, 2022 (verified from SerpAPI iso_date, last edited Feb 15, 2022)",
    "review_date_source": "verified_serpapi",
    "has_text": true,
    "text_note": null,
    "brand_name": "inkOUT",
    "multi_location_brand": true,
    "location_transition": false,
    "transition_note": null
  },
  {
    "provider_name": "inkOUT",
    "location_city": "Draper",
    "location_state": "UT",
    "method_used": "TEPR",
    "review_text": "Jazz is incredible to work with, she is extremely knowledgeable in her field and went above and beyond to help answer all my questions, as well as kind and personable. Long sessions can sometimes mean long awkward silence  but not with Jazz:) I could chat with her all day!  She made me comfortable and calm like I was with an old friend. 10/10 experience.",
    "star_rating": 5,
    "review_date": "4 years ago",
    "review_date_iso": "2022-02-11T23:03:27Z",
    "review_date_edited_iso": "2022-02-11T23:03:27Z",
    "reviewer_name": "Sarah Winkler",
    "reviewer_local_guide": true,
    "verified_source": "Google",
    "_place_title": "Rejuvatek Aesthetics providing inkOUT®",
    "_place_id": "ChIJwZ1KoJ6HUocRpaZ0Pq0XQaU",
    "_scrape_mode": "full",
    "_scrape_date": "2026-04-24",
    "source_url": "https://www.google.com/maps/reviews/data=!4m8!14m7!1m6!2m5!1sChdDSUhNMG9nS0VJQ0FnSURtbC12aGtBRRAB!2m1!1s0x0:0xa54117ad3e74a6a5!3m1!1s2@1:CIHM0ogKEICAgIDml-vhkAE%7C%7C?hl=en",
    "pain_level": "unknown",
    "scarring_mentioned": "No",
    "sessions_completed": "unknown",
    "skin_type": "unknown",
    "use_case": "unknown",
    "result_rating": "Positive",
    "review_date_estimated": "2022-02-11",
    "review_date_label": "Feb 11, 2022 (verified from SerpAPI iso_date, last edited Feb 11, 2022)",
    "review_date_source": "verified_serpapi",
    "has_text": true,
    "text_note": null,
    "brand_name": "inkOUT",
    "multi_location_brand": true,
    "location_transition": false,
    "transition_note": null
  },
  {
    "provider_name": "inkOUT",
    "location_city": "Draper",
    "location_state": "UT",
    "method_used": "TEPR",
    "review_text": "Jazz Wilkey has been such a delight to work with on my tattoo removal! She is always willing to answer any questions I have about my own removal process and information all around! I am grateful to have come across such a patient team, and I recommend Tatt2Away to anyone looking for a safe way to remove their tattoos!",
    "star_rating": 5,
    "review_date": "4 years ago",
    "review_date_iso": "2021-09-15T23:40:43Z",
    "review_date_edited_iso": "2021-09-15T23:40:43Z",
    "reviewer_name": "Jiana Ford",
    "reviewer_local_guide": true,
    "verified_source": "Google",
    "_place_title": "Rejuvatek Aesthetics providing inkOUT®",
    "_place_id": "ChIJwZ1KoJ6HUocRpaZ0Pq0XQaU",
    "_scrape_mode": "full",
    "_scrape_date": "2026-04-24",
    "source_url": "https://www.google.com/maps/reviews/data=!4m8!14m7!1m6!2m5!1sChdDSUhNMG9nS0VJQ0FnSUM2ajVlTzBBRRAB!2m1!1s0x0:0xa54117ad3e74a6a5!3m1!1s2@1:CIHM0ogKEICAgIC6j5eO0AE%7C%7C?hl=en",
    "pain_level": "unknown",
    "scarring_mentioned": "No",
    "sessions_completed": "unknown",
    "skin_type": "unknown",
    "use_case": "Complete",
    "result_rating": "Positive",
    "review_date_estimated": "2021-09-15",
    "review_date_label": "Sep 15, 2021 (verified from SerpAPI iso_date, last edited Sep 15, 2021)",
    "review_date_source": "verified_serpapi",
    "has_text": true,
    "text_note": null,
    "brand_name": "inkOUT",
    "multi_location_brand": true,
    "location_transition": false,
    "transition_note": null
  },
  {
    "provider_name": "inkOUT",
    "location_city": "Draper",
    "location_state": "UT",
    "method_used": "TEPR",
    "review_text": "Jazz is the sweetest lady ever. she made me feel so comfortable during my appointment, she is so personable and is the very best!",
    "star_rating": 5,
    "review_date": "4 years ago",
    "review_date_iso": "2021-09-15T22:36:41Z",
    "review_date_edited_iso": "2021-09-15T22:36:41Z",
    "reviewer_name": "kass tonc",
    "reviewer_local_guide": true,
    "verified_source": "Google",
    "_place_title": "Rejuvatek Aesthetics providing inkOUT®",
    "_place_id": "ChIJwZ1KoJ6HUocRpaZ0Pq0XQaU",
    "_scrape_mode": "full",
    "_scrape_date": "2026-04-24",
    "source_url": "https://www.google.com/maps/reviews/data=!4m8!14m7!1m6!2m5!1sChdDSUhNMG9nS0VJQ0FnSUM2ajcydTdnRRAB!2m1!1s0x0:0xa54117ad3e74a6a5!3m1!1s2@1:CIHM0ogKEICAgIC6j72u7gE%7C%7C?hl=en",
    "pain_level": "unknown",
    "scarring_mentioned": "No",
    "sessions_completed": "unknown",
    "skin_type": "unknown",
    "use_case": "unknown",
    "result_rating": "Positive",
    "review_date_estimated": "2021-09-15",
    "review_date_label": "Sep 15, 2021 (verified from SerpAPI iso_date, last edited Sep 15, 2021)",
    "review_date_source": "verified_serpapi",
    "has_text": true,
    "text_note": null,
    "brand_name": "inkOUT",
    "multi_location_brand": true,
    "location_transition": false,
    "transition_note": null
  },
  {
    "provider_name": "inkOUT",
    "location_city": "Draper",
    "location_state": "UT",
    "method_used": "TEPR",
    "review_text": "I have currently had my first session with Jazz done and I’m about 4 weeks into my healing process. The little scabs have all come off and I can see this beautifully pink healthy ink free skin underneath! I’m excited to see what happens after number 2!\nJazz is a delightful human! I really enjoyed the time we got to spend together doing my appointment. She’s super knowledgeable and has zero problem with any questions!",
    "star_rating": 5,
    "review_date": "4 years ago",
    "review_date_iso": "2021-09-11T00:44:17Z",
    "review_date_edited_iso": "2021-09-11T00:44:17Z",
    "reviewer_name": "Aspen McKenna",
    "reviewer_local_guide": true,
    "verified_source": "Google",
    "_place_title": "Rejuvatek Aesthetics providing inkOUT®",
    "_place_id": "ChIJwZ1KoJ6HUocRpaZ0Pq0XQaU",
    "_scrape_mode": "full",
    "_scrape_date": "2026-04-24",
    "source_url": "https://www.google.com/maps/reviews/data=!4m8!14m7!1m6!2m5!1sChdDSUhNMG9nS0VJQ0FnSUM2dmVXbTB3RRAB!2m1!1s0x0:0xa54117ad3e74a6a5!3m1!1s2@1:CIHM0ogKEICAgIC6veWm0wE%7C%7C?hl=en",
    "pain_level": "unknown",
    "scarring_mentioned": "Positive",
    "sessions_completed": 1,
    "skin_type": "unknown",
    "use_case": "Complete",
    "result_rating": "Positive",
    "review_date_estimated": "2021-09-11",
    "review_date_label": "Sep 11, 2021 (verified from SerpAPI iso_date, last edited Sep 11, 2021)",
    "review_date_source": "verified_serpapi",
    "has_text": true,
    "text_note": null,
    "brand_name": "inkOUT",
    "multi_location_brand": true,
    "location_transition": false,
    "transition_note": null
  }
]